{
  "_cacheVersion": "20260321-v2",
  "source": "official-filings",
  "ticker": "AMZN",
  "cik": 1018724,
  "axis": "ProductOrServiceAxis",
  "quarters": {
    "2018Q1": [
      {
        "name": "Online Stores",
        "memberKey": "onlinestores",
        "valueBn": 26.939,
        "sourceUrl": "https://www.sec.gov/Archives/edgar/data/1018724/000101872419000043/amzn-20190331.xml",
        "sourceForm": "10-Q",
        "filingDate": "2019-04-26",
        "periodStart": "2018-01-01",
        "periodEnd": "2018-03-31"
      },
      {
        "name": "Third Party Seller Services",
        "memberKey": "thirdpartysellerservices",
        "valueBn": 9.265,
        "sourceUrl": "https://www.sec.gov/Archives/edgar/data/1018724/000101872419000043/amzn-20190331.xml",
        "sourceForm": "10-Q",
        "filingDate": "2019-04-26",
        "periodStart": "2018-01-01",
        "periodEnd": "2018-03-31"
      },
      {
        "name": "Amazon Web Services",
        "memberKey": "amazonwebservices",
        "valueBn": 5.442,
        "sourceUrl": "https://www.sec.gov/Archives/edgar/data/1018724/000101872419000043/amzn-20190331.xml",
        "sourceForm": "10-Q",
        "filingDate": "2019-04-26",
        "periodStart": "2018-01-01",
        "periodEnd": "2018-03-31"
      },
      {
        "name": "Physical Stores",
        "memberKey": "physicalstores",
        "valueBn": 4.263,
        "sourceUrl": "https://www.sec.gov/Archives/edgar/data/1018724/000101872419000043/amzn-20190331.xml",
        "sourceForm": "10-Q",
        "filingDate": "2019-04-26",
        "periodStart": "2018-01-01",
        "periodEnd": "2018-03-31"
      },
      {
        "name": "Subscription Services",
        "memberKey": "subscriptionservices",
        "valueBn": 3.102,
        "sourceUrl": "https://www.sec.gov/Archives/edgar/data/1018724/000101872419000043/amzn-20190331.xml",
        "sourceForm": "10-Q",
        "filingDate": "2019-04-26",
        "periodStart": "2018-01-01",
        "periodEnd": "2018-03-31"
      },
      {
        "name": "Other Services",
        "memberKey": "otherservices",
        "valueBn": 2.031,
        "sourceUrl": "https://www.sec.gov/Archives/edgar/data/1018724/000101872419000043/amzn-20190331.xml",
        "sourceForm": "10-Q",
        "filingDate": "2019-04-26",
        "periodStart": "2018-01-01",
        "periodEnd": "2018-03-31"
      }
    ],
    "2018Q2": [
      {
        "name": "Online Stores",
        "memberKey": "onlinestores",
        "valueBn": 27.165,
        "sourceUrl": "https://www.sec.gov/Archives/edgar/data/1018724/000101872419000071/amzn-2019630x10q_htm.xml",
        "sourceForm": "10-Q",
        "filingDate": "2019-07-26",
        "periodStart": "2018-04-01",
        "periodEnd": "2018-06-30"
      },
      {
        "name": "Third Party Seller Services",
        "memberKey": "thirdpartysellerservices",
        "valueBn": 9.702,
        "sourceUrl": "https://www.sec.gov/Archives/edgar/data/1018724/000101872419000071/amzn-2019630x10q_htm.xml",
        "sourceForm": "10-Q",
        "filingDate": "2019-07-26",
        "periodStart": "2018-04-01",
        "periodEnd": "2018-06-30"
      },
      {
        "name": "Amazon Web Services",
        "memberKey": "amazonwebservices",
        "valueBn": 6.105,
        "sourceUrl": "https://www.sec.gov/Archives/edgar/data/1018724/000101872419000071/amzn-2019630x10q_htm.xml",
        "sourceForm": "10-Q",
        "filingDate": "2019-07-26",
        "periodStart": "2018-04-01",
        "periodEnd": "2018-06-30"
      },
      {
        "name": "Physical Stores",
        "memberKey": "physicalstores",
        "valueBn": 4.312,
        "sourceUrl": "https://www.sec.gov/Archives/edgar/data/1018724/000101872419000071/amzn-2019630x10q_htm.xml",
        "sourceForm": "10-Q",
        "filingDate": "2019-07-26",
        "periodStart": "2018-04-01",
        "periodEnd": "2018-06-30"
      },
      {
        "name": "Subscription Services",
        "memberKey": "subscriptionservices",
        "valueBn": 3.408,
        "sourceUrl": "https://www.sec.gov/Archives/edgar/data/1018724/000101872419000071/amzn-2019630x10q_htm.xml",
        "sourceForm": "10-Q",
        "filingDate": "2019-07-26",
        "periodStart": "2018-04-01",
        "periodEnd": "2018-06-30"
      },
      {
        "name": "Other Services",
        "memberKey": "otherservices",
        "valueBn": 2.194,
        "sourceUrl": "https://www.sec.gov/Archives/edgar/data/1018724/000101872419000071/amzn-2019630x10q_htm.xml",
        "sourceForm": "10-Q",
        "filingDate": "2019-07-26",
        "periodStart": "2018-04-01",
        "periodEnd": "2018-06-30"
      }
    ],
    "2018Q3": [
      {
        "name": "Online Stores",
        "memberKey": "onlinestores",
        "valueBn": 29.061,
        "sourceUrl": "https://www.sec.gov/Archives/edgar/data/1018724/000101872419000089/amzn-2019930x10q_htm.xml",
        "sourceForm": "10-Q",
        "filingDate": "2019-10-25",
        "periodStart": "2018-07-01",
        "periodEnd": "2018-09-30"
      },
      {
        "name": "Third Party Seller Services",
        "memberKey": "thirdpartysellerservices",
        "valueBn": 10.395,
        "sourceUrl": "https://www.sec.gov/Archives/edgar/data/1018724/000101872419000089/amzn-2019930x10q_htm.xml",
        "sourceForm": "10-Q",
        "filingDate": "2019-10-25",
        "periodStart": "2018-07-01",
        "periodEnd": "2018-09-30"
      },
      {
        "name": "Amazon Web Services",
        "memberKey": "amazonwebservices",
        "valueBn": 6.679,
        "sourceUrl": "https://www.sec.gov/Archives/edgar/data/1018724/000101872419000089/amzn-2019930x10q_htm.xml",
        "sourceForm": "10-Q",
        "filingDate": "2019-10-25",
        "periodStart": "2018-07-01",
        "periodEnd": "2018-09-30"
      },
      {
        "name": "Physical Stores",
        "memberKey": "physicalstores",
        "valueBn": 4.248,
        "sourceUrl": "https://www.sec.gov/Archives/edgar/data/1018724/000101872419000089/amzn-2019930x10q_htm.xml",
        "sourceForm": "10-Q",
        "filingDate": "2019-10-25",
        "periodStart": "2018-07-01",
        "periodEnd": "2018-09-30"
      },
      {
        "name": "Subscription Services",
        "memberKey": "subscriptionservices",
        "valueBn": 3.698,
        "sourceUrl": "https://www.sec.gov/Archives/edgar/data/1018724/000101872419000089/amzn-2019930x10q_htm.xml",
        "sourceForm": "10-Q",
        "filingDate": "2019-10-25",
        "periodStart": "2018-07-01",
        "periodEnd": "2018-09-30"
      },
      {
        "name": "Other Services",
        "memberKey": "otherservices",
        "valueBn": 2.495,
        "sourceUrl": "https://www.sec.gov/Archives/edgar/data/1018724/000101872419000089/amzn-2019930x10q_htm.xml",
        "sourceForm": "10-Q",
        "filingDate": "2019-10-25",
        "periodStart": "2018-07-01",
        "periodEnd": "2018-09-30"
      }
    ],
    "2018Q4": [
      {
        "name": "Online Stores",
        "memberKey": "onlinestores",
        "valueBn": 39.822,
        "sourceUrl": "https://www.sec.gov/Archives/edgar/data/1018724/000101872420000004/amzn-20191231x10k_htm.xml",
        "sourceForm": "10-K",
        "filingDate": "2020-01-31",
        "periodStart": "2018-10-01",
        "periodEnd": "2018-12-31"
      },
      {
        "name": "Third Party Seller Services",
        "memberKey": "thirdpartysellerservices",
        "valueBn": 13.383,
        "sourceUrl": "https://www.sec.gov/Archives/edgar/data/1018724/000101872420000004/amzn-20191231x10k_htm.xml",
        "sourceForm": "10-K",
        "filingDate": "2020-01-31",
        "periodStart": "2018-10-01",
        "periodEnd": "2018-12-31"
      },
      {
        "name": "Amazon Web Services",
        "memberKey": "amazonwebservices",
        "valueBn": 7.429,
        "sourceUrl": "https://www.sec.gov/Archives/edgar/data/1018724/000101872420000004/amzn-20191231x10k_htm.xml",
        "sourceForm": "10-K",
        "filingDate": "2020-01-31",
        "periodStart": "2018-10-01",
        "periodEnd": "2018-12-31"
      },
      {
        "name": "Physical Stores",
        "memberKey": "physicalstores",
        "valueBn": 4.401,
        "sourceUrl": "https://www.sec.gov/Archives/edgar/data/1018724/000101872420000004/amzn-20191231x10k_htm.xml",
        "sourceForm": "10-K",
        "filingDate": "2020-01-31",
        "periodStart": "2018-10-01",
        "periodEnd": "2018-12-31"
      },
      {
        "name": "Subscription Services",
        "memberKey": "subscriptionservices",
        "valueBn": 3.96,
        "sourceUrl": "https://www.sec.gov/Archives/edgar/data/1018724/000101872420000004/amzn-20191231x10k_htm.xml",
        "sourceForm": "10-K",
        "filingDate": "2020-01-31",
        "periodStart": "2018-10-01",
        "periodEnd": "2018-12-31"
      },
      {
        "name": "Other Services",
        "memberKey": "otherservices",
        "valueBn": 3.388,
        "sourceUrl": "https://www.sec.gov/Archives/edgar/data/1018724/000101872420000004/amzn-20191231x10k_htm.xml",
        "sourceForm": "10-K",
        "filingDate": "2020-01-31",
        "periodStart": "2018-10-01",
        "periodEnd": "2018-12-31"
      }
    ],
    "2019Q1": [
      {
        "name": "Online Stores",
        "memberKey": "onlinestores",
        "valueBn": 29.498,
        "sourceUrl": "https://www.sec.gov/Archives/edgar/data/1018724/000101872419000043/amzn-20190331.xml",
        "sourceForm": "10-Q",
        "filingDate": "2019-04-26",
        "periodStart": "2019-01-01",
        "periodEnd": "2019-03-31"
      },
      {
        "name": "Third Party Seller Services",
        "memberKey": "thirdpartysellerservices",
        "valueBn": 11.141,
        "sourceUrl": "https://www.sec.gov/Archives/edgar/data/1018724/000101872419000043/amzn-20190331.xml",
        "sourceForm": "10-Q",
        "filingDate": "2019-04-26",
        "periodStart": "2019-01-01",
        "periodEnd": "2019-03-31"
      },
      {
        "name": "Amazon Web Services",
        "memberKey": "amazonwebservices",
        "valueBn": 7.696,
        "sourceUrl": "https://www.sec.gov/Archives/edgar/data/1018724/000101872419000043/amzn-20190331.xml",
        "sourceForm": "10-Q",
        "filingDate": "2019-04-26",
        "periodStart": "2019-01-01",
        "periodEnd": "2019-03-31"
      },
      {
        "name": "Subscription Services",
        "memberKey": "subscriptionservices",
        "valueBn": 4.342,
        "sourceUrl": "https://www.sec.gov/Archives/edgar/data/1018724/000101872419000043/amzn-20190331.xml",
        "sourceForm": "10-Q",
        "filingDate": "2019-04-26",
        "periodStart": "2019-01-01",
        "periodEnd": "2019-03-31"
      },
      {
        "name": "Physical Stores",
        "memberKey": "physicalstores",
        "valueBn": 4.307,
        "sourceUrl": "https://www.sec.gov/Archives/edgar/data/1018724/000101872419000043/amzn-20190331.xml",
        "sourceForm": "10-Q",
        "filingDate": "2019-04-26",
        "periodStart": "2019-01-01",
        "periodEnd": "2019-03-31"
      },
      {
        "name": "Other Services",
        "memberKey": "otherservices",
        "valueBn": 2.716,
        "sourceUrl": "https://www.sec.gov/Archives/edgar/data/1018724/000101872419000043/amzn-20190331.xml",
        "sourceForm": "10-Q",
        "filingDate": "2019-04-26",
        "periodStart": "2019-01-01",
        "periodEnd": "2019-03-31"
      }
    ],
    "2019Q2": [
      {
        "name": "Online Stores",
        "memberKey": "onlinestores",
        "valueBn": 31.053,
        "sourceUrl": "https://www.sec.gov/Archives/edgar/data/1018724/000101872419000071/amzn-2019630x10q_htm.xml",
        "sourceForm": "10-Q",
        "filingDate": "2019-07-26",
        "periodStart": "2019-04-01",
        "periodEnd": "2019-06-30"
      },
      {
        "name": "Third Party Seller Services",
        "memberKey": "thirdpartysellerservices",
        "valueBn": 11.962,
        "sourceUrl": "https://www.sec.gov/Archives/edgar/data/1018724/000101872419000071/amzn-2019630x10q_htm.xml",
        "sourceForm": "10-Q",
        "filingDate": "2019-07-26",
        "periodStart": "2019-04-01",
        "periodEnd": "2019-06-30"
      },
      {
        "name": "Amazon Web Services",
        "memberKey": "amazonwebservices",
        "valueBn": 8.381,
        "sourceUrl": "https://www.sec.gov/Archives/edgar/data/1018724/000101872419000071/amzn-2019630x10q_htm.xml",
        "sourceForm": "10-Q",
        "filingDate": "2019-07-26",
        "periodStart": "2019-04-01",
        "periodEnd": "2019-06-30"
      },
      {
        "name": "Subscription Services",
        "memberKey": "subscriptionservices",
        "valueBn": 4.676,
        "sourceUrl": "https://www.sec.gov/Archives/edgar/data/1018724/000101872419000071/amzn-2019630x10q_htm.xml",
        "sourceForm": "10-Q",
        "filingDate": "2019-07-26",
        "periodStart": "2019-04-01",
        "periodEnd": "2019-06-30"
      },
      {
        "name": "Physical Stores",
        "memberKey": "physicalstores",
        "valueBn": 4.33,
        "sourceUrl": "https://www.sec.gov/Archives/edgar/data/1018724/000101872419000071/amzn-2019630x10q_htm.xml",
        "sourceForm": "10-Q",
        "filingDate": "2019-07-26",
        "periodStart": "2019-04-01",
        "periodEnd": "2019-06-30"
      },
      {
        "name": "Other Services",
        "memberKey": "otherservices",
        "valueBn": 3.002,
        "sourceUrl": "https://www.sec.gov/Archives/edgar/data/1018724/000101872419000071/amzn-2019630x10q_htm.xml",
        "sourceForm": "10-Q",
        "filingDate": "2019-07-26",
        "periodStart": "2019-04-01",
        "periodEnd": "2019-06-30"
      }
    ],
    "2019Q3": [
      {
        "name": "Online Stores",
        "memberKey": "onlinestores",
        "valueBn": 35.039,
        "sourceUrl": "https://www.sec.gov/Archives/edgar/data/1018724/000101872419000089/amzn-2019930x10q_htm.xml",
        "sourceForm": "10-Q",
        "filingDate": "2019-10-25",
        "periodStart": "2019-07-01",
        "periodEnd": "2019-09-30"
      },
      {
        "name": "Third Party Seller Services",
        "memberKey": "thirdpartysellerservices",
        "valueBn": 13.212,
        "sourceUrl": "https://www.sec.gov/Archives/edgar/data/1018724/000101872419000089/amzn-2019930x10q_htm.xml",
        "sourceForm": "10-Q",
        "filingDate": "2019-10-25",
        "periodStart": "2019-07-01",
        "periodEnd": "2019-09-30"
      },
      {
        "name": "Amazon Web Services",
        "memberKey": "amazonwebservices",
        "valueBn": 8.995,
        "sourceUrl": "https://www.sec.gov/Archives/edgar/data/1018724/000101872419000089/amzn-2019930x10q_htm.xml",
        "sourceForm": "10-Q",
        "filingDate": "2019-10-25",
        "periodStart": "2019-07-01",
        "periodEnd": "2019-09-30"
      },
      {
        "name": "Subscription Services",
        "memberKey": "subscriptionservices",
        "valueBn": 4.957,
        "sourceUrl": "https://www.sec.gov/Archives/edgar/data/1018724/000101872419000089/amzn-2019930x10q_htm.xml",
        "sourceForm": "10-Q",
        "filingDate": "2019-10-25",
        "periodStart": "2019-07-01",
        "periodEnd": "2019-09-30"
      },
      {
        "name": "Physical Stores",
        "memberKey": "physicalstores",
        "valueBn": 4.192,
        "sourceUrl": "https://www.sec.gov/Archives/edgar/data/1018724/000101872419000089/amzn-2019930x10q_htm.xml",
        "sourceForm": "10-Q",
        "filingDate": "2019-10-25",
        "periodStart": "2019-07-01",
        "periodEnd": "2019-09-30"
      },
      {
        "name": "Other Services",
        "memberKey": "otherservices",
        "valueBn": 3.586,
        "sourceUrl": "https://www.sec.gov/Archives/edgar/data/1018724/000101872419000089/amzn-2019930x10q_htm.xml",
        "sourceForm": "10-Q",
        "filingDate": "2019-10-25",
        "periodStart": "2019-07-01",
        "periodEnd": "2019-09-30"
      }
    ],
    "2019Q4": [
      {
        "name": "Online Stores",
        "memberKey": "onlinestores",
        "valueBn": 45.657,
        "sourceUrl": "https://www.sec.gov/Archives/edgar/data/1018724/000101872420000004/amzn-20191231x10k_htm.xml",
        "sourceForm": "10-K",
        "filingDate": "2020-01-31",
        "periodStart": "2019-10-01",
        "periodEnd": "2019-12-31"
      },
      {
        "name": "Third Party Seller Services",
        "memberKey": "thirdpartysellerservices",
        "valueBn": 17.447,
        "sourceUrl": "https://www.sec.gov/Archives/edgar/data/1018724/000101872420000004/amzn-20191231x10k_htm.xml",
        "sourceForm": "10-K",
        "filingDate": "2020-01-31",
        "periodStart": "2019-10-01",
        "periodEnd": "2019-12-31"
      },
      {
        "name": "Amazon Web Services",
        "memberKey": "amazonwebservices",
        "valueBn": 9.954,
        "sourceUrl": "https://www.sec.gov/Archives/edgar/data/1018724/000101872420000004/amzn-20191231x10k_htm.xml",
        "sourceForm": "10-K",
        "filingDate": "2020-01-31",
        "periodStart": "2019-10-01",
        "periodEnd": "2019-12-31"
      },
      {
        "name": "Subscription Services",
        "memberKey": "subscriptionservices",
        "valueBn": 5.235,
        "sourceUrl": "https://www.sec.gov/Archives/edgar/data/1018724/000101872420000004/amzn-20191231x10k_htm.xml",
        "sourceForm": "10-K",
        "filingDate": "2020-01-31",
        "periodStart": "2019-10-01",
        "periodEnd": "2019-12-31"
      },
      {
        "name": "Other Services",
        "memberKey": "otherservices",
        "valueBn": 4.781,
        "sourceUrl": "https://www.sec.gov/Archives/edgar/data/1018724/000101872420000004/amzn-20191231x10k_htm.xml",
        "sourceForm": "10-K",
        "filingDate": "2020-01-31",
        "periodStart": "2019-10-01",
        "periodEnd": "2019-12-31"
      },
      {
        "name": "Physical Stores",
        "memberKey": "physicalstores",
        "valueBn": 4.363,
        "sourceUrl": "https://www.sec.gov/Archives/edgar/data/1018724/000101872420000004/amzn-20191231x10k_htm.xml",
        "sourceForm": "10-K",
        "filingDate": "2020-01-31",
        "periodStart": "2019-10-01",
        "periodEnd": "2019-12-31"
      }
    ],
    "2020Q1": [
      {
        "name": "Online Stores",
        "memberKey": "onlinestores",
        "valueBn": 36.652,
        "sourceUrl": "https://www.sec.gov/Archives/edgar/data/1018724/000101872420000010/amzn-20200331x10q_htm.xml",
        "sourceForm": "10-Q",
        "filingDate": "2020-05-01",
        "periodStart": "2020-01-01",
        "periodEnd": "2020-03-31"
      },
      {
        "name": "Third Party Seller Services",
        "memberKey": "thirdpartysellerservices",
        "valueBn": 14.479,
        "sourceUrl": "https://www.sec.gov/Archives/edgar/data/1018724/000101872420000010/amzn-20200331x10q_htm.xml",
        "sourceForm": "10-Q",
        "filingDate": "2020-05-01",
        "periodStart": "2020-01-01",
        "periodEnd": "2020-03-31"
      },
      {
        "name": "Amazon Web Services",
        "memberKey": "amazonwebservices",
        "valueBn": 10.219,
        "sourceUrl": "https://www.sec.gov/Archives/edgar/data/1018724/000101872420000010/amzn-20200331x10q_htm.xml",
        "sourceForm": "10-Q",
        "filingDate": "2020-05-01",
        "periodStart": "2020-01-01",
        "periodEnd": "2020-03-31"
      },
      {
        "name": "Subscription Services",
        "memberKey": "subscriptionservices",
        "valueBn": 5.556,
        "sourceUrl": "https://www.sec.gov/Archives/edgar/data/1018724/000101872420000010/amzn-20200331x10q_htm.xml",
        "sourceForm": "10-Q",
        "filingDate": "2020-05-01",
        "periodStart": "2020-01-01",
        "periodEnd": "2020-03-31"
      },
      {
        "name": "Physical Stores",
        "memberKey": "physicalstores",
        "valueBn": 4.64,
        "sourceUrl": "https://www.sec.gov/Archives/edgar/data/1018724/000101872420000010/amzn-20200331x10q_htm.xml",
        "sourceForm": "10-Q",
        "filingDate": "2020-05-01",
        "periodStart": "2020-01-01",
        "periodEnd": "2020-03-31"
      },
      {
        "name": "Other Services",
        "memberKey": "otherservices",
        "valueBn": 3.906,
        "sourceUrl": "https://www.sec.gov/Archives/edgar/data/1018724/000101872420000010/amzn-20200331x10q_htm.xml",
        "sourceForm": "10-Q",
        "filingDate": "2020-05-01",
        "periodStart": "2020-01-01",
        "periodEnd": "2020-03-31"
      }
    ],
    "2020Q2": [
      {
        "name": "Online Stores",
        "memberKey": "onlinestores",
        "valueBn": 45.896,
        "sourceUrl": "https://www.sec.gov/Archives/edgar/data/1018724/000101872420000021/amzn-20200630_htm.xml",
        "sourceForm": "10-Q",
        "filingDate": "2020-07-31",
        "periodStart": "2020-04-01",
        "periodEnd": "2020-06-30"
      },
      {
        "name": "Third Party Seller Services",
        "memberKey": "thirdpartysellerservices",
        "valueBn": 18.195,
        "sourceUrl": "https://www.sec.gov/Archives/edgar/data/1018724/000101872420000021/amzn-20200630_htm.xml",
        "sourceForm": "10-Q",
        "filingDate": "2020-07-31",
        "periodStart": "2020-04-01",
        "periodEnd": "2020-06-30"
      },
      {
        "name": "Amazon Web Services",
        "memberKey": "amazonwebservices",
        "valueBn": 10.808,
        "sourceUrl": "https://www.sec.gov/Archives/edgar/data/1018724/000101872420000021/amzn-20200630_htm.xml",
        "sourceForm": "10-Q",
        "filingDate": "2020-07-31",
        "periodStart": "2020-04-01",
        "periodEnd": "2020-06-30"
      },
      {
        "name": "Subscription Services",
        "memberKey": "subscriptionservices",
        "valueBn": 6.018,
        "sourceUrl": "https://www.sec.gov/Archives/edgar/data/1018724/000101872420000021/amzn-20200630_htm.xml",
        "sourceForm": "10-Q",
        "filingDate": "2020-07-31",
        "periodStart": "2020-04-01",
        "periodEnd": "2020-06-30"
      },
      {
        "name": "Other Services",
        "memberKey": "otherservices",
        "valueBn": 4.221,
        "sourceUrl": "https://www.sec.gov/Archives/edgar/data/1018724/000101872420000021/amzn-20200630_htm.xml",
        "sourceForm": "10-Q",
        "filingDate": "2020-07-31",
        "periodStart": "2020-04-01",
        "periodEnd": "2020-06-30"
      },
      {
        "name": "Physical Stores",
        "memberKey": "physicalstores",
        "valueBn": 3.774,
        "sourceUrl": "https://www.sec.gov/Archives/edgar/data/1018724/000101872420000021/amzn-20200630_htm.xml",
        "sourceForm": "10-Q",
        "filingDate": "2020-07-31",
        "periodStart": "2020-04-01",
        "periodEnd": "2020-06-30"
      }
    ],
    "2020Q3": [
      {
        "name": "Online Stores",
        "memberKey": "onlinestores",
        "valueBn": 48.35,
        "sourceUrl": "https://www.sec.gov/Archives/edgar/data/1018724/000101872420000030/amzn-20200930_htm.xml",
        "sourceForm": "10-Q",
        "filingDate": "2020-10-30",
        "periodStart": "2020-07-01",
        "periodEnd": "2020-09-30"
      },
      {
        "name": "Third Party Seller Services",
        "memberKey": "thirdpartysellerservices",
        "valueBn": 20.436,
        "sourceUrl": "https://www.sec.gov/Archives/edgar/data/1018724/000101872420000030/amzn-20200930_htm.xml",
        "sourceForm": "10-Q",
        "filingDate": "2020-10-30",
        "periodStart": "2020-07-01",
        "periodEnd": "2020-09-30"
      },
      {
        "name": "Amazon Web Services",
        "memberKey": "amazonwebservices",
        "valueBn": 11.601,
        "sourceUrl": "https://www.sec.gov/Archives/edgar/data/1018724/000101872420000030/amzn-20200930_htm.xml",
        "sourceForm": "10-Q",
        "filingDate": "2020-10-30",
        "periodStart": "2020-07-01",
        "periodEnd": "2020-09-30"
      },
      {
        "name": "Subscription Services",
        "memberKey": "subscriptionservices",
        "valueBn": 6.572,
        "sourceUrl": "https://www.sec.gov/Archives/edgar/data/1018724/000101872420000030/amzn-20200930_htm.xml",
        "sourceForm": "10-Q",
        "filingDate": "2020-10-30",
        "periodStart": "2020-07-01",
        "periodEnd": "2020-09-30"
      },
      {
        "name": "Other Services",
        "memberKey": "otherservices",
        "valueBn": 5.398,
        "sourceUrl": "https://www.sec.gov/Archives/edgar/data/1018724/000101872420000030/amzn-20200930_htm.xml",
        "sourceForm": "10-Q",
        "filingDate": "2020-10-30",
        "periodStart": "2020-07-01",
        "periodEnd": "2020-09-30"
      },
      {
        "name": "Physical Stores",
        "memberKey": "physicalstores",
        "valueBn": 3.788,
        "sourceUrl": "https://www.sec.gov/Archives/edgar/data/1018724/000101872420000030/amzn-20200930_htm.xml",
        "sourceForm": "10-Q",
        "filingDate": "2020-10-30",
        "periodStart": "2020-07-01",
        "periodEnd": "2020-09-30"
      }
    ],
    "2020Q4": [
      {
        "name": "Online Stores",
        "memberKey": "onlinestores",
        "valueBn": 66.448,
        "sourceUrl": "https://www.sec.gov/Archives/edgar/data/1018724/000101872421000004/amzn-20201231_htm.xml",
        "sourceForm": "10-K",
        "filingDate": "2021-02-03",
        "periodStart": "2020-10-01",
        "periodEnd": "2020-12-31"
      },
      {
        "name": "Third Party Seller Services",
        "memberKey": "thirdpartysellerservices",
        "valueBn": 27.351,
        "sourceUrl": "https://www.sec.gov/Archives/edgar/data/1018724/000101872421000004/amzn-20201231_htm.xml",
        "sourceForm": "10-K",
        "filingDate": "2021-02-03",
        "periodStart": "2020-10-01",
        "periodEnd": "2020-12-31"
      },
      {
        "name": "Amazon Web Services",
        "memberKey": "amazonwebservices",
        "valueBn": 12.742,
        "sourceUrl": "https://www.sec.gov/Archives/edgar/data/1018724/000101872421000004/amzn-20201231_htm.xml",
        "sourceForm": "10-K",
        "filingDate": "2021-02-03",
        "periodStart": "2020-10-01",
        "periodEnd": "2020-12-31"
      },
      {
        "name": "Other Services",
        "memberKey": "otherservices",
        "valueBn": 7.928,
        "sourceUrl": "https://www.sec.gov/Archives/edgar/data/1018724/000101872421000004/amzn-20201231_htm.xml",
        "sourceForm": "10-K",
        "filingDate": "2021-02-03",
        "periodStart": "2020-10-01",
        "periodEnd": "2020-12-31"
      },
      {
        "name": "Subscription Services",
        "memberKey": "subscriptionservices",
        "valueBn": 7.061,
        "sourceUrl": "https://www.sec.gov/Archives/edgar/data/1018724/000101872421000004/amzn-20201231_htm.xml",
        "sourceForm": "10-K",
        "filingDate": "2021-02-03",
        "periodStart": "2020-10-01",
        "periodEnd": "2020-12-31"
      },
      {
        "name": "Physical Stores",
        "memberKey": "physicalstores",
        "valueBn": 4.025,
        "sourceUrl": "https://www.sec.gov/Archives/edgar/data/1018724/000101872421000004/amzn-20201231_htm.xml",
        "sourceForm": "10-K",
        "filingDate": "2021-02-03",
        "periodStart": "2020-10-01",
        "periodEnd": "2020-12-31"
      }
    ],
    "2021Q1": [
      {
        "name": "Online Stores",
        "memberKey": "onlinestores",
        "valueBn": 52.901,
        "sourceUrl": "https://www.sec.gov/Archives/edgar/data/1018724/000101872421000010/amzn-20210331_htm.xml",
        "sourceForm": "10-Q",
        "filingDate": "2021-04-30",
        "periodStart": "2021-01-01",
        "periodEnd": "2021-03-31"
      },
      {
        "name": "Third Party Seller Services",
        "memberKey": "thirdpartysellerservices",
        "valueBn": 23.709,
        "sourceUrl": "https://www.sec.gov/Archives/edgar/data/1018724/000101872421000010/amzn-20210331_htm.xml",
        "sourceForm": "10-Q",
        "filingDate": "2021-04-30",
        "periodStart": "2021-01-01",
        "periodEnd": "2021-03-31"
      },
      {
        "name": "Amazon Web Services",
        "memberKey": "amazonwebservices",
        "valueBn": 13.503,
        "sourceUrl": "https://www.sec.gov/Archives/edgar/data/1018724/000101872421000010/amzn-20210331_htm.xml",
        "sourceForm": "10-Q",
        "filingDate": "2021-04-30",
        "periodStart": "2021-01-01",
        "periodEnd": "2021-03-31"
      },
      {
        "name": "Subscription Services",
        "memberKey": "subscriptionservices",
        "valueBn": 7.58,
        "sourceUrl": "https://www.sec.gov/Archives/edgar/data/1018724/000101872421000010/amzn-20210331_htm.xml",
        "sourceForm": "10-Q",
        "filingDate": "2021-04-30",
        "periodStart": "2021-01-01",
        "periodEnd": "2021-03-31"
      },
      {
        "name": "Other Services",
        "memberKey": "otherservices",
        "valueBn": 6.905,
        "sourceUrl": "https://www.sec.gov/Archives/edgar/data/1018724/000101872421000010/amzn-20210331_htm.xml",
        "sourceForm": "10-Q",
        "filingDate": "2021-04-30",
        "periodStart": "2021-01-01",
        "periodEnd": "2021-03-31"
      },
      {
        "name": "Advertising Services",
        "memberKey": "advertisingservices",
        "valueBn": 6.381,
        "sourceUrl": "https://www.sec.gov/Archives/edgar/data/1018724/000101872422000013/amzn-20220331_htm.xml",
        "sourceForm": "10-Q",
        "filingDate": "2022-04-29",
        "periodStart": "2021-01-01",
        "periodEnd": "2021-03-31"
      },
      {
        "name": "Physical Stores",
        "memberKey": "physicalstores",
        "valueBn": 3.92,
        "sourceUrl": "https://www.sec.gov/Archives/edgar/data/1018724/000101872421000010/amzn-20210331_htm.xml",
        "sourceForm": "10-Q",
        "filingDate": "2021-04-30",
        "periodStart": "2021-01-01",
        "periodEnd": "2021-03-31"
      }
    ],
    "2021Q2": [
      {
        "name": "Online Stores",
        "memberKey": "onlinestores",
        "valueBn": 53.157,
        "sourceUrl": "https://www.sec.gov/Archives/edgar/data/1018724/000101872421000020/amzn-20210630_htm.xml",
        "sourceForm": "10-Q",
        "filingDate": "2021-07-30",
        "periodStart": "2021-04-01",
        "periodEnd": "2021-06-30"
      },
      {
        "name": "Third Party Seller Services",
        "memberKey": "thirdpartysellerservices",
        "valueBn": 25.085,
        "sourceUrl": "https://www.sec.gov/Archives/edgar/data/1018724/000101872421000020/amzn-20210630_htm.xml",
        "sourceForm": "10-Q",
        "filingDate": "2021-07-30",
        "periodStart": "2021-04-01",
        "periodEnd": "2021-06-30"
      },
      {
        "name": "Amazon Web Services",
        "memberKey": "amazonwebservices",
        "valueBn": 14.809,
        "sourceUrl": "https://www.sec.gov/Archives/edgar/data/1018724/000101872421000020/amzn-20210630_htm.xml",
        "sourceForm": "10-Q",
        "filingDate": "2021-07-30",
        "periodStart": "2021-04-01",
        "periodEnd": "2021-06-30"
      },
      {
        "name": "Subscription Services",
        "memberKey": "subscriptionservices",
        "valueBn": 7.917,
        "sourceUrl": "https://www.sec.gov/Archives/edgar/data/1018724/000101872421000020/amzn-20210630_htm.xml",
        "sourceForm": "10-Q",
        "filingDate": "2021-07-30",
        "periodStart": "2021-04-01",
        "periodEnd": "2021-06-30"
      },
      {
        "name": "Other Services",
        "memberKey": "otherservices",
        "valueBn": 7.914,
        "sourceUrl": "https://www.sec.gov/Archives/edgar/data/1018724/000101872421000020/amzn-20210630_htm.xml",
        "sourceForm": "10-Q",
        "filingDate": "2021-07-30",
        "periodStart": "2021-04-01",
        "periodEnd": "2021-06-30"
      },
      {
        "name": "Advertising Services",
        "memberKey": "advertisingservices",
        "valueBn": 7.451,
        "sourceUrl": "https://www.sec.gov/Archives/edgar/data/1018724/000101872422000019/amzn-20220630_htm.xml",
        "sourceForm": "10-Q",
        "filingDate": "2022-07-29",
        "periodStart": "2021-04-01",
        "periodEnd": "2021-06-30"
      },
      {
        "name": "Physical Stores",
        "memberKey": "physicalstores",
        "valueBn": 4.198,
        "sourceUrl": "https://www.sec.gov/Archives/edgar/data/1018724/000101872421000020/amzn-20210630_htm.xml",
        "sourceForm": "10-Q",
        "filingDate": "2021-07-30",
        "periodStart": "2021-04-01",
        "periodEnd": "2021-06-30"
      }
    ],
    "2021Q3": [
      {
        "name": "Online Stores",
        "memberKey": "onlinestores",
        "valueBn": 49.942,
        "sourceUrl": "https://www.sec.gov/Archives/edgar/data/1018724/000101872421000028/amzn-20210930_htm.xml",
        "sourceForm": "10-Q",
        "filingDate": "2021-10-29",
        "periodStart": "2021-07-01",
        "periodEnd": "2021-09-30"
      },
      {
        "name": "Third Party Seller Services",
        "memberKey": "thirdpartysellerservices",
        "valueBn": 24.252,
        "sourceUrl": "https://www.sec.gov/Archives/edgar/data/1018724/000101872421000028/amzn-20210930_htm.xml",
        "sourceForm": "10-Q",
        "filingDate": "2021-10-29",
        "periodStart": "2021-07-01",
        "periodEnd": "2021-09-30"
      },
      {
        "name": "Amazon Web Services",
        "memberKey": "amazonwebservices",
        "valueBn": 16.11,
        "sourceUrl": "https://www.sec.gov/Archives/edgar/data/1018724/000101872421000028/amzn-20210930_htm.xml",
        "sourceForm": "10-Q",
        "filingDate": "2021-10-29",
        "periodStart": "2021-07-01",
        "periodEnd": "2021-09-30"
      },
      {
        "name": "Subscription Services",
        "memberKey": "subscriptionservices",
        "valueBn": 8.148,
        "sourceUrl": "https://www.sec.gov/Archives/edgar/data/1018724/000101872421000028/amzn-20210930_htm.xml",
        "sourceForm": "10-Q",
        "filingDate": "2021-10-29",
        "periodStart": "2021-07-01",
        "periodEnd": "2021-09-30"
      },
      {
        "name": "Other Services",
        "memberKey": "otherservices",
        "valueBn": 8.091,
        "sourceUrl": "https://www.sec.gov/Archives/edgar/data/1018724/000101872421000028/amzn-20210930_htm.xml",
        "sourceForm": "10-Q",
        "filingDate": "2021-10-29",
        "periodStart": "2021-07-01",
        "periodEnd": "2021-09-30"
      },
      {
        "name": "Advertising Services",
        "memberKey": "advertisingservices",
        "valueBn": 7.612,
        "sourceUrl": "https://www.sec.gov/Archives/edgar/data/1018724/000101872422000023/amzn-20220930_htm.xml",
        "sourceForm": "10-Q",
        "filingDate": "2022-10-28",
        "periodStart": "2021-07-01",
        "periodEnd": "2021-09-30"
      },
      {
        "name": "Physical Stores",
        "memberKey": "physicalstores",
        "valueBn": 4.269,
        "sourceUrl": "https://www.sec.gov/Archives/edgar/data/1018724/000101872421000028/amzn-20210930_htm.xml",
        "sourceForm": "10-Q",
        "filingDate": "2021-10-29",
        "periodStart": "2021-07-01",
        "periodEnd": "2021-09-30"
      }
    ],
    "2021Q4": [
      {
        "name": "Online Stores",
        "memberKey": "onlinestores",
        "valueBn": 66.075,
        "sourceUrl": "https://www.sec.gov/Archives/edgar/data/1018724/000101872422000005/amzn-20211231_htm.xml",
        "sourceForm": "10-K",
        "filingDate": "2022-02-04",
        "periodStart": "2021-10-01",
        "periodEnd": "2021-12-31"
      },
      {
        "name": "Third Party Seller Services",
        "memberKey": "thirdpartysellerservices",
        "valueBn": 30.32,
        "sourceUrl": "https://www.sec.gov/Archives/edgar/data/1018724/000101872422000005/amzn-20211231_htm.xml",
        "sourceForm": "10-K",
        "filingDate": "2022-02-04",
        "periodStart": "2021-10-01",
        "periodEnd": "2021-12-31"
      },
      {
        "name": "Amazon Web Services",
        "memberKey": "amazonwebservices",
        "valueBn": 17.78,
        "sourceUrl": "https://www.sec.gov/Archives/edgar/data/1018724/000101872422000005/amzn-20211231_htm.xml",
        "sourceForm": "10-K",
        "filingDate": "2022-02-04",
        "periodStart": "2021-10-01",
        "periodEnd": "2021-12-31"
      },
      {
        "name": "Subscription Services",
        "memberKey": "subscriptionservices",
        "valueBn": 8.123,
        "sourceUrl": "https://www.sec.gov/Archives/edgar/data/1018724/000101872422000005/amzn-20211231_htm.xml",
        "sourceForm": "10-K",
        "filingDate": "2022-02-04",
        "periodStart": "2021-10-01",
        "periodEnd": "2021-12-31"
      },
      {
        "name": "Physical Stores",
        "memberKey": "physicalstores",
        "valueBn": 4.688,
        "sourceUrl": "https://www.sec.gov/Archives/edgar/data/1018724/000101872422000005/amzn-20211231_htm.xml",
        "sourceForm": "10-K",
        "filingDate": "2022-02-04",
        "periodStart": "2021-10-01",
        "periodEnd": "2021-12-31"
      }
    ],
    "2022Q1": [
      {
        "name": "Online Stores",
        "memberKey": "onlinestores",
        "valueBn": 51.129,
        "sourceUrl": "https://www.sec.gov/Archives/edgar/data/1018724/000101872422000013/amzn-20220331_htm.xml",
        "sourceForm": "10-Q",
        "filingDate": "2022-04-29",
        "periodStart": "2022-01-01",
        "periodEnd": "2022-03-31"
      },
      {
        "name": "Third Party Seller Services",
        "memberKey": "thirdpartysellerservices",
        "valueBn": 25.335,
        "sourceUrl": "https://www.sec.gov/Archives/edgar/data/1018724/000101872422000013/amzn-20220331_htm.xml",
        "sourceForm": "10-Q",
        "filingDate": "2022-04-29",
        "periodStart": "2022-01-01",
        "periodEnd": "2022-03-31"
      },
      {
        "name": "Amazon Web Services",
        "memberKey": "amazonwebservices",
        "valueBn": 18.441,
        "sourceUrl": "https://www.sec.gov/Archives/edgar/data/1018724/000101872422000013/amzn-20220331_htm.xml",
        "sourceForm": "10-Q",
        "filingDate": "2022-04-29",
        "periodStart": "2022-01-01",
        "periodEnd": "2022-03-31"
      },
      {
        "name": "Subscription Services",
        "memberKey": "subscriptionservices",
        "valueBn": 8.41,
        "sourceUrl": "https://www.sec.gov/Archives/edgar/data/1018724/000101872422000013/amzn-20220331_htm.xml",
        "sourceForm": "10-Q",
        "filingDate": "2022-04-29",
        "periodStart": "2022-01-01",
        "periodEnd": "2022-03-31"
      },
      {
        "name": "Advertising Services",
        "memberKey": "advertisingservices",
        "valueBn": 7.877,
        "sourceUrl": "https://www.sec.gov/Archives/edgar/data/1018724/000101872422000013/amzn-20220331_htm.xml",
        "sourceForm": "10-Q",
        "filingDate": "2022-04-29",
        "periodStart": "2022-01-01",
        "periodEnd": "2022-03-31"
      },
      {
        "name": "Physical Stores",
        "memberKey": "physicalstores",
        "valueBn": 4.591,
        "sourceUrl": "https://www.sec.gov/Archives/edgar/data/1018724/000101872422000013/amzn-20220331_htm.xml",
        "sourceForm": "10-Q",
        "filingDate": "2022-04-29",
        "periodStart": "2022-01-01",
        "periodEnd": "2022-03-31"
      },
      {
        "name": "Other Services",
        "memberKey": "otherservices",
        "valueBn": 0.661,
        "sourceUrl": "https://www.sec.gov/Archives/edgar/data/1018724/000101872422000013/amzn-20220331_htm.xml",
        "sourceForm": "10-Q",
        "filingDate": "2022-04-29",
        "periodStart": "2022-01-01",
        "periodEnd": "2022-03-31"
      }
    ],
    "2022Q2": [
      {
        "name": "Online Stores",
        "memberKey": "onlinestores",
        "valueBn": 50.855,
        "sourceUrl": "https://www.sec.gov/Archives/edgar/data/1018724/000101872422000019/amzn-20220630_htm.xml",
        "sourceForm": "10-Q",
        "filingDate": "2022-07-29",
        "periodStart": "2022-04-01",
        "periodEnd": "2022-06-30"
      },
      {
        "name": "Third Party Seller Services",
        "memberKey": "thirdpartysellerservices",
        "valueBn": 27.376,
        "sourceUrl": "https://www.sec.gov/Archives/edgar/data/1018724/000101872422000019/amzn-20220630_htm.xml",
        "sourceForm": "10-Q",
        "filingDate": "2022-07-29",
        "periodStart": "2022-04-01",
        "periodEnd": "2022-06-30"
      },
      {
        "name": "Amazon Web Services",
        "memberKey": "amazonwebservices",
        "valueBn": 19.739,
        "sourceUrl": "https://www.sec.gov/Archives/edgar/data/1018724/000101872422000019/amzn-20220630_htm.xml",
        "sourceForm": "10-Q",
        "filingDate": "2022-07-29",
        "periodStart": "2022-04-01",
        "periodEnd": "2022-06-30"
      },
      {
        "name": "Advertising Services",
        "memberKey": "advertisingservices",
        "valueBn": 8.757,
        "sourceUrl": "https://www.sec.gov/Archives/edgar/data/1018724/000101872422000019/amzn-20220630_htm.xml",
        "sourceForm": "10-Q",
        "filingDate": "2022-07-29",
        "periodStart": "2022-04-01",
        "periodEnd": "2022-06-30"
      },
      {
        "name": "Subscription Services",
        "memberKey": "subscriptionservices",
        "valueBn": 8.716,
        "sourceUrl": "https://www.sec.gov/Archives/edgar/data/1018724/000101872422000019/amzn-20220630_htm.xml",
        "sourceForm": "10-Q",
        "filingDate": "2022-07-29",
        "periodStart": "2022-04-01",
        "periodEnd": "2022-06-30"
      },
      {
        "name": "Physical Stores",
        "memberKey": "physicalstores",
        "valueBn": 4.721,
        "sourceUrl": "https://www.sec.gov/Archives/edgar/data/1018724/000101872422000019/amzn-20220630_htm.xml",
        "sourceForm": "10-Q",
        "filingDate": "2022-07-29",
        "periodStart": "2022-04-01",
        "periodEnd": "2022-06-30"
      },
      {
        "name": "Other Services",
        "memberKey": "otherservices",
        "valueBn": 1.07,
        "sourceUrl": "https://www.sec.gov/Archives/edgar/data/1018724/000101872422000019/amzn-20220630_htm.xml",
        "sourceForm": "10-Q",
        "filingDate": "2022-07-29",
        "periodStart": "2022-04-01",
        "periodEnd": "2022-06-30"
      }
    ],
    "2022Q3": [
      {
        "name": "Online Stores",
        "memberKey": "onlinestores",
        "valueBn": 53.489,
        "sourceUrl": "https://www.sec.gov/Archives/edgar/data/1018724/000101872422000023/amzn-20220930_htm.xml",
        "sourceForm": "10-Q",
        "filingDate": "2022-10-28",
        "periodStart": "2022-07-01",
        "periodEnd": "2022-09-30"
      },
      {
        "name": "Third Party Seller Services",
        "memberKey": "thirdpartysellerservices",
        "valueBn": 28.666,
        "sourceUrl": "https://www.sec.gov/Archives/edgar/data/1018724/000101872422000023/amzn-20220930_htm.xml",
        "sourceForm": "10-Q",
        "filingDate": "2022-10-28",
        "periodStart": "2022-07-01",
        "periodEnd": "2022-09-30"
      },
      {
        "name": "Amazon Web Services",
        "memberKey": "amazonwebservices",
        "valueBn": 20.538,
        "sourceUrl": "https://www.sec.gov/Archives/edgar/data/1018724/000101872422000023/amzn-20220930_htm.xml",
        "sourceForm": "10-Q",
        "filingDate": "2022-10-28",
        "periodStart": "2022-07-01",
        "periodEnd": "2022-09-30"
      },
      {
        "name": "Advertising Services",
        "memberKey": "advertisingservices",
        "valueBn": 9.548,
        "sourceUrl": "https://www.sec.gov/Archives/edgar/data/1018724/000101872422000023/amzn-20220930_htm.xml",
        "sourceForm": "10-Q",
        "filingDate": "2022-10-28",
        "periodStart": "2022-07-01",
        "periodEnd": "2022-09-30"
      },
      {
        "name": "Subscription Services",
        "memberKey": "subscriptionservices",
        "valueBn": 8.903,
        "sourceUrl": "https://www.sec.gov/Archives/edgar/data/1018724/000101872422000023/amzn-20220930_htm.xml",
        "sourceForm": "10-Q",
        "filingDate": "2022-10-28",
        "periodStart": "2022-07-01",
        "periodEnd": "2022-09-30"
      },
      {
        "name": "Physical Stores",
        "memberKey": "physicalstores",
        "valueBn": 4.694,
        "sourceUrl": "https://www.sec.gov/Archives/edgar/data/1018724/000101872422000023/amzn-20220930_htm.xml",
        "sourceForm": "10-Q",
        "filingDate": "2022-10-28",
        "periodStart": "2022-07-01",
        "periodEnd": "2022-09-30"
      },
      {
        "name": "Other Services",
        "memberKey": "otherservices",
        "valueBn": 1.263,
        "sourceUrl": "https://www.sec.gov/Archives/edgar/data/1018724/000101872422000023/amzn-20220930_htm.xml",
        "sourceForm": "10-Q",
        "filingDate": "2022-10-28",
        "periodStart": "2022-07-01",
        "periodEnd": "2022-09-30"
      }
    ],
    "2022Q4": [
      {
        "name": "Online Stores",
        "memberKey": "onlinestores",
        "valueBn": 64.531,
        "sourceUrl": "https://www.sec.gov/Archives/edgar/data/1018724/000101872423000004/amzn-20221231_htm.xml",
        "sourceForm": "10-K",
        "filingDate": "2023-02-03",
        "periodStart": "2022-10-01",
        "periodEnd": "2022-12-31"
      },
      {
        "name": "Third Party Seller Services",
        "memberKey": "thirdpartysellerservices",
        "valueBn": 36.339,
        "sourceUrl": "https://www.sec.gov/Archives/edgar/data/1018724/000101872423000004/amzn-20221231_htm.xml",
        "sourceForm": "10-K",
        "filingDate": "2023-02-03",
        "periodStart": "2022-10-01",
        "periodEnd": "2022-12-31"
      },
      {
        "name": "Amazon Web Services",
        "memberKey": "amazonwebservices",
        "valueBn": 21.378,
        "sourceUrl": "https://www.sec.gov/Archives/edgar/data/1018724/000101872423000004/amzn-20221231_htm.xml",
        "sourceForm": "10-K",
        "filingDate": "2023-02-03",
        "periodStart": "2022-10-01",
        "periodEnd": "2022-12-31"
      },
      {
        "name": "Subscription Services",
        "memberKey": "subscriptionservices",
        "valueBn": 9.189,
        "sourceUrl": "https://www.sec.gov/Archives/edgar/data/1018724/000101872423000004/amzn-20221231_htm.xml",
        "sourceForm": "10-K",
        "filingDate": "2023-02-03",
        "periodStart": "2022-10-01",
        "periodEnd": "2022-12-31"
      },
      {
        "name": "Physical Stores",
        "memberKey": "physicalstores",
        "valueBn": 4.957,
        "sourceUrl": "https://www.sec.gov/Archives/edgar/data/1018724/000101872423000004/amzn-20221231_htm.xml",
        "sourceForm": "10-K",
        "filingDate": "2023-02-03",
        "periodStart": "2022-10-01",
        "periodEnd": "2022-12-31"
      },
      {
        "name": "Other Services",
        "memberKey": "otherservices",
        "valueBn": 1.253,
        "sourceUrl": "https://www.sec.gov/Archives/edgar/data/1018724/000101872423000004/amzn-20221231_htm.xml",
        "sourceForm": "10-K",
        "filingDate": "2023-02-03",
        "periodStart": "2022-10-01",
        "periodEnd": "2022-12-31"
      }
    ],
    "2023Q1": [
      {
        "name": "Online Stores",
        "memberKey": "onlinestores",
        "valueBn": 51.096,
        "sourceUrl": "https://www.sec.gov/Archives/edgar/data/1018724/000101872423000008/amzn-20230331_htm.xml",
        "sourceForm": "10-Q",
        "filingDate": "2023-04-28",
        "periodStart": "2023-01-01",
        "periodEnd": "2023-03-31"
      },
      {
        "name": "Third Party Seller Services",
        "memberKey": "thirdpartysellerservices",
        "valueBn": 29.82,
        "sourceUrl": "https://www.sec.gov/Archives/edgar/data/1018724/000101872423000008/amzn-20230331_htm.xml",
        "sourceForm": "10-Q",
        "filingDate": "2023-04-28",
        "periodStart": "2023-01-01",
        "periodEnd": "2023-03-31"
      },
      {
        "name": "Amazon Web Services",
        "memberKey": "amazonwebservices",
        "valueBn": 21.354,
        "sourceUrl": "https://www.sec.gov/Archives/edgar/data/1018724/000101872423000008/amzn-20230331_htm.xml",
        "sourceForm": "10-Q",
        "filingDate": "2023-04-28",
        "periodStart": "2023-01-01",
        "periodEnd": "2023-03-31"
      },
      {
        "name": "Subscription Services",
        "memberKey": "subscriptionservices",
        "valueBn": 9.657,
        "sourceUrl": "https://www.sec.gov/Archives/edgar/data/1018724/000101872423000008/amzn-20230331_htm.xml",
        "sourceForm": "10-Q",
        "filingDate": "2023-04-28",
        "periodStart": "2023-01-01",
        "periodEnd": "2023-03-31"
      },
      {
        "name": "Advertising Services",
        "memberKey": "advertisingservices",
        "valueBn": 9.509,
        "sourceUrl": "https://www.sec.gov/Archives/edgar/data/1018724/000101872423000008/amzn-20230331_htm.xml",
        "sourceForm": "10-Q",
        "filingDate": "2023-04-28",
        "periodStart": "2023-01-01",
        "periodEnd": "2023-03-31"
      },
      {
        "name": "Physical Stores",
        "memberKey": "physicalstores",
        "valueBn": 4.895,
        "sourceUrl": "https://www.sec.gov/Archives/edgar/data/1018724/000101872423000008/amzn-20230331_htm.xml",
        "sourceForm": "10-Q",
        "filingDate": "2023-04-28",
        "periodStart": "2023-01-01",
        "periodEnd": "2023-03-31"
      },
      {
        "name": "Other Services",
        "memberKey": "otherservices",
        "valueBn": 1.027,
        "sourceUrl": "https://www.sec.gov/Archives/edgar/data/1018724/000101872423000008/amzn-20230331_htm.xml",
        "sourceForm": "10-Q",
        "filingDate": "2023-04-28",
        "periodStart": "2023-01-01",
        "periodEnd": "2023-03-31"
      }
    ],
    "2023Q2": [
      {
        "name": "Online Stores",
        "memberKey": "onlinestores",
        "valueBn": 52.966,
        "sourceUrl": "https://www.sec.gov/Archives/edgar/data/1018724/000101872423000012/amzn-20230630_htm.xml",
        "sourceForm": "10-Q",
        "filingDate": "2023-08-04",
        "periodStart": "2023-04-01",
        "periodEnd": "2023-06-30"
      },
      {
        "name": "Third Party Seller Services",
        "memberKey": "thirdpartysellerservices",
        "valueBn": 32.332,
        "sourceUrl": "https://www.sec.gov/Archives/edgar/data/1018724/000101872423000012/amzn-20230630_htm.xml",
        "sourceForm": "10-Q",
        "filingDate": "2023-08-04",
        "periodStart": "2023-04-01",
        "periodEnd": "2023-06-30"
      },
      {
        "name": "Amazon Web Services",
        "memberKey": "amazonwebservices",
        "valueBn": 22.14,
        "sourceUrl": "https://www.sec.gov/Archives/edgar/data/1018724/000101872423000012/amzn-20230630_htm.xml",
        "sourceForm": "10-Q",
        "filingDate": "2023-08-04",
        "periodStart": "2023-04-01",
        "periodEnd": "2023-06-30"
      },
      {
        "name": "Advertising Services",
        "memberKey": "advertisingservices",
        "valueBn": 10.683,
        "sourceUrl": "https://www.sec.gov/Archives/edgar/data/1018724/000101872423000012/amzn-20230630_htm.xml",
        "sourceForm": "10-Q",
        "filingDate": "2023-08-04",
        "periodStart": "2023-04-01",
        "periodEnd": "2023-06-30"
      },
      {
        "name": "Subscription Services",
        "memberKey": "subscriptionservices",
        "valueBn": 9.894,
        "sourceUrl": "https://www.sec.gov/Archives/edgar/data/1018724/000101872423000012/amzn-20230630_htm.xml",
        "sourceForm": "10-Q",
        "filingDate": "2023-08-04",
        "periodStart": "2023-04-01",
        "periodEnd": "2023-06-30"
      },
      {
        "name": "Physical Stores",
        "memberKey": "physicalstores",
        "valueBn": 5.024,
        "sourceUrl": "https://www.sec.gov/Archives/edgar/data/1018724/000101872423000012/amzn-20230630_htm.xml",
        "sourceForm": "10-Q",
        "filingDate": "2023-08-04",
        "periodStart": "2023-04-01",
        "periodEnd": "2023-06-30"
      },
      {
        "name": "Other Services",
        "memberKey": "otherservices",
        "valueBn": 1.344,
        "sourceUrl": "https://www.sec.gov/Archives/edgar/data/1018724/000101872423000012/amzn-20230630_htm.xml",
        "sourceForm": "10-Q",
        "filingDate": "2023-08-04",
        "periodStart": "2023-04-01",
        "periodEnd": "2023-06-30"
      }
    ],
    "2023Q3": [
      {
        "name": "Online Stores",
        "memberKey": "onlinestores",
        "valueBn": 57.267,
        "sourceUrl": "https://www.sec.gov/Archives/edgar/data/1018724/000101872423000018/amzn-20230930_htm.xml",
        "sourceForm": "10-Q",
        "filingDate": "2023-10-27",
        "periodStart": "2023-07-01",
        "periodEnd": "2023-09-30"
      },
      {
        "name": "Third Party Seller Services",
        "memberKey": "thirdpartysellerservices",
        "valueBn": 34.342,
        "sourceUrl": "https://www.sec.gov/Archives/edgar/data/1018724/000101872423000018/amzn-20230930_htm.xml",
        "sourceForm": "10-Q",
        "filingDate": "2023-10-27",
        "periodStart": "2023-07-01",
        "periodEnd": "2023-09-30"
      },
      {
        "name": "Amazon Web Services",
        "memberKey": "amazonwebservices",
        "valueBn": 23.059,
        "sourceUrl": "https://www.sec.gov/Archives/edgar/data/1018724/000101872423000018/amzn-20230930_htm.xml",
        "sourceForm": "10-Q",
        "filingDate": "2023-10-27",
        "periodStart": "2023-07-01",
        "periodEnd": "2023-09-30"
      },
      {
        "name": "Advertising Services",
        "memberKey": "advertisingservices",
        "valueBn": 12.06,
        "sourceUrl": "https://www.sec.gov/Archives/edgar/data/1018724/000101872423000018/amzn-20230930_htm.xml",
        "sourceForm": "10-Q",
        "filingDate": "2023-10-27",
        "periodStart": "2023-07-01",
        "periodEnd": "2023-09-30"
      },
      {
        "name": "Subscription Services",
        "memberKey": "subscriptionservices",
        "valueBn": 10.17,
        "sourceUrl": "https://www.sec.gov/Archives/edgar/data/1018724/000101872423000018/amzn-20230930_htm.xml",
        "sourceForm": "10-Q",
        "filingDate": "2023-10-27",
        "periodStart": "2023-07-01",
        "periodEnd": "2023-09-30"
      },
      {
        "name": "Physical Stores",
        "memberKey": "physicalstores",
        "valueBn": 4.959,
        "sourceUrl": "https://www.sec.gov/Archives/edgar/data/1018724/000101872423000018/amzn-20230930_htm.xml",
        "sourceForm": "10-Q",
        "filingDate": "2023-10-27",
        "periodStart": "2023-07-01",
        "periodEnd": "2023-09-30"
      },
      {
        "name": "Other Services",
        "memberKey": "otherservices",
        "valueBn": 1.226,
        "sourceUrl": "https://www.sec.gov/Archives/edgar/data/1018724/000101872423000018/amzn-20230930_htm.xml",
        "sourceForm": "10-Q",
        "filingDate": "2023-10-27",
        "periodStart": "2023-07-01",
        "periodEnd": "2023-09-30"
      }
    ],
    "2023Q4": [
      {
        "name": "Online Stores",
        "memberKey": "onlinestores",
        "valueBn": 70.543,
        "sourceUrl": "https://www.sec.gov/Archives/edgar/data/1018724/000101872424000008/amzn-20231231_htm.xml",
        "sourceForm": "10-K",
        "filingDate": "2024-02-02",
        "periodStart": "2023-10-01",
        "periodEnd": "2023-12-31"
      },
      {
        "name": "Third Party Seller Services",
        "memberKey": "thirdpartysellerservices",
        "valueBn": 43.559,
        "sourceUrl": "https://www.sec.gov/Archives/edgar/data/1018724/000101872424000008/amzn-20231231_htm.xml",
        "sourceForm": "10-K",
        "filingDate": "2024-02-02",
        "periodStart": "2023-10-01",
        "periodEnd": "2023-12-31"
      },
      {
        "name": "Amazon Web Services",
        "memberKey": "amazonwebservices",
        "valueBn": 24.204,
        "sourceUrl": "https://www.sec.gov/Archives/edgar/data/1018724/000101872424000008/amzn-20231231_htm.xml",
        "sourceForm": "10-K",
        "filingDate": "2024-02-02",
        "periodStart": "2023-10-01",
        "periodEnd": "2023-12-31"
      },
      {
        "name": "Subscription Services",
        "memberKey": "subscriptionservices",
        "valueBn": 10.488,
        "sourceUrl": "https://www.sec.gov/Archives/edgar/data/1018724/000101872424000008/amzn-20231231_htm.xml",
        "sourceForm": "10-K",
        "filingDate": "2024-02-02",
        "periodStart": "2023-10-01",
        "periodEnd": "2023-12-31"
      },
      {
        "name": "Physical Stores",
        "memberKey": "physicalstores",
        "valueBn": 5.152,
        "sourceUrl": "https://www.sec.gov/Archives/edgar/data/1018724/000101872424000008/amzn-20231231_htm.xml",
        "sourceForm": "10-K",
        "filingDate": "2024-02-02",
        "periodStart": "2023-10-01",
        "periodEnd": "2023-12-31"
      },
      {
        "name": "Other Services",
        "memberKey": "otherservices",
        "valueBn": 1.361,
        "sourceUrl": "https://www.sec.gov/Archives/edgar/data/1018724/000101872424000008/amzn-20231231_htm.xml",
        "sourceForm": "10-K",
        "filingDate": "2024-02-02",
        "periodStart": "2023-10-01",
        "periodEnd": "2023-12-31"
      }
    ],
    "2024Q1": [
      {
        "name": "Online Stores",
        "memberKey": "onlinestores",
        "valueBn": 54.67,
        "sourceUrl": "https://www.sec.gov/Archives/edgar/data/1018724/000101872424000083/amzn-20240331_htm.xml",
        "sourceForm": "10-Q",
        "filingDate": "2024-05-01",
        "periodStart": "2024-01-01",
        "periodEnd": "2024-03-31"
      },
      {
        "name": "Third Party Seller Services",
        "memberKey": "thirdpartysellerservices",
        "valueBn": 34.596,
        "sourceUrl": "https://www.sec.gov/Archives/edgar/data/1018724/000101872424000083/amzn-20240331_htm.xml",
        "sourceForm": "10-Q",
        "filingDate": "2024-05-01",
        "periodStart": "2024-01-01",
        "periodEnd": "2024-03-31"
      },
      {
        "name": "Amazon Web Services",
        "memberKey": "amazonwebservices",
        "valueBn": 25.037,
        "sourceUrl": "https://www.sec.gov/Archives/edgar/data/1018724/000101872424000083/amzn-20240331_htm.xml",
        "sourceForm": "10-Q",
        "filingDate": "2024-05-01",
        "periodStart": "2024-01-01",
        "periodEnd": "2024-03-31"
      },
      {
        "name": "Advertising Services",
        "memberKey": "advertisingservices",
        "valueBn": 11.824,
        "sourceUrl": "https://www.sec.gov/Archives/edgar/data/1018724/000101872424000083/amzn-20240331_htm.xml",
        "sourceForm": "10-Q",
        "filingDate": "2024-05-01",
        "periodStart": "2024-01-01",
        "periodEnd": "2024-03-31"
      },
      {
        "name": "Subscription Services",
        "memberKey": "subscriptionservices",
        "valueBn": 10.722,
        "sourceUrl": "https://www.sec.gov/Archives/edgar/data/1018724/000101872424000083/amzn-20240331_htm.xml",
        "sourceForm": "10-Q",
        "filingDate": "2024-05-01",
        "periodStart": "2024-01-01",
        "periodEnd": "2024-03-31"
      },
      {
        "name": "Physical Stores",
        "memberKey": "physicalstores",
        "valueBn": 5.202,
        "sourceUrl": "https://www.sec.gov/Archives/edgar/data/1018724/000101872424000083/amzn-20240331_htm.xml",
        "sourceForm": "10-Q",
        "filingDate": "2024-05-01",
        "periodStart": "2024-01-01",
        "periodEnd": "2024-03-31"
      },
      {
        "name": "Other Services",
        "memberKey": "otherservices",
        "valueBn": 1.262,
        "sourceUrl": "https://www.sec.gov/Archives/edgar/data/1018724/000101872424000083/amzn-20240331_htm.xml",
        "sourceForm": "10-Q",
        "filingDate": "2024-05-01",
        "periodStart": "2024-01-01",
        "periodEnd": "2024-03-31"
      }
    ],
    "2024Q2": [
      {
        "name": "Online Stores",
        "memberKey": "onlinestores",
        "valueBn": 55.392,
        "sourceUrl": "https://www.sec.gov/Archives/edgar/data/1018724/000101872424000130/amzn-20240630_htm.xml",
        "sourceForm": "10-Q",
        "filingDate": "2024-08-02",
        "periodStart": "2024-04-01",
        "periodEnd": "2024-06-30"
      },
      {
        "name": "Third Party Seller Services",
        "memberKey": "thirdpartysellerservices",
        "valueBn": 36.201,
        "sourceUrl": "https://www.sec.gov/Archives/edgar/data/1018724/000101872424000130/amzn-20240630_htm.xml",
        "sourceForm": "10-Q",
        "filingDate": "2024-08-02",
        "periodStart": "2024-04-01",
        "periodEnd": "2024-06-30"
      },
      {
        "name": "Amazon Web Services",
        "memberKey": "amazonwebservices",
        "valueBn": 26.281,
        "sourceUrl": "https://www.sec.gov/Archives/edgar/data/1018724/000101872424000130/amzn-20240630_htm.xml",
        "sourceForm": "10-Q",
        "filingDate": "2024-08-02",
        "periodStart": "2024-04-01",
        "periodEnd": "2024-06-30"
      },
      {
        "name": "Advertising Services",
        "memberKey": "advertisingservices",
        "valueBn": 12.771,
        "sourceUrl": "https://www.sec.gov/Archives/edgar/data/1018724/000101872424000130/amzn-20240630_htm.xml",
        "sourceForm": "10-Q",
        "filingDate": "2024-08-02",
        "periodStart": "2024-04-01",
        "periodEnd": "2024-06-30"
      },
      {
        "name": "Subscription Services",
        "memberKey": "subscriptionservices",
        "valueBn": 10.866,
        "sourceUrl": "https://www.sec.gov/Archives/edgar/data/1018724/000101872424000130/amzn-20240630_htm.xml",
        "sourceForm": "10-Q",
        "filingDate": "2024-08-02",
        "periodStart": "2024-04-01",
        "periodEnd": "2024-06-30"
      },
      {
        "name": "Physical Stores",
        "memberKey": "physicalstores",
        "valueBn": 5.206,
        "sourceUrl": "https://www.sec.gov/Archives/edgar/data/1018724/000101872424000130/amzn-20240630_htm.xml",
        "sourceForm": "10-Q",
        "filingDate": "2024-08-02",
        "periodStart": "2024-04-01",
        "periodEnd": "2024-06-30"
      },
      {
        "name": "Other Services",
        "memberKey": "otherservices",
        "valueBn": 1.26,
        "sourceUrl": "https://www.sec.gov/Archives/edgar/data/1018724/000101872424000130/amzn-20240630_htm.xml",
        "sourceForm": "10-Q",
        "filingDate": "2024-08-02",
        "periodStart": "2024-04-01",
        "periodEnd": "2024-06-30"
      }
    ],
    "2024Q3": [
      {
        "name": "Online Stores",
        "memberKey": "onlinestores",
        "valueBn": 61.411,
        "sourceUrl": "https://www.sec.gov/Archives/edgar/data/1018724/000101872424000161/amzn-20240930_htm.xml",
        "sourceForm": "10-Q",
        "filingDate": "2024-11-01",
        "periodStart": "2024-07-01",
        "periodEnd": "2024-09-30"
      },
      {
        "name": "Third Party Seller Services",
        "memberKey": "thirdpartysellerservices",
        "valueBn": 37.864,
        "sourceUrl": "https://www.sec.gov/Archives/edgar/data/1018724/000101872424000161/amzn-20240930_htm.xml",
        "sourceForm": "10-Q",
        "filingDate": "2024-11-01",
        "periodStart": "2024-07-01",
        "periodEnd": "2024-09-30"
      },
      {
        "name": "Amazon Web Services",
        "memberKey": "amazonwebservices",
        "valueBn": 27.452,
        "sourceUrl": "https://www.sec.gov/Archives/edgar/data/1018724/000101872424000161/amzn-20240930_htm.xml",
        "sourceForm": "10-Q",
        "filingDate": "2024-11-01",
        "periodStart": "2024-07-01",
        "periodEnd": "2024-09-30"
      },
      {
        "name": "Advertising Services",
        "memberKey": "advertisingservices",
        "valueBn": 14.331,
        "sourceUrl": "https://www.sec.gov/Archives/edgar/data/1018724/000101872424000161/amzn-20240930_htm.xml",
        "sourceForm": "10-Q",
        "filingDate": "2024-11-01",
        "periodStart": "2024-07-01",
        "periodEnd": "2024-09-30"
      },
      {
        "name": "Subscription Services",
        "memberKey": "subscriptionservices",
        "valueBn": 11.278,
        "sourceUrl": "https://www.sec.gov/Archives/edgar/data/1018724/000101872424000161/amzn-20240930_htm.xml",
        "sourceForm": "10-Q",
        "filingDate": "2024-11-01",
        "periodStart": "2024-07-01",
        "periodEnd": "2024-09-30"
      },
      {
        "name": "Physical Stores",
        "memberKey": "physicalstores",
        "valueBn": 5.228,
        "sourceUrl": "https://www.sec.gov/Archives/edgar/data/1018724/000101872424000161/amzn-20240930_htm.xml",
        "sourceForm": "10-Q",
        "filingDate": "2024-11-01",
        "periodStart": "2024-07-01",
        "periodEnd": "2024-09-30"
      },
      {
        "name": "Other Services",
        "memberKey": "otherservices",
        "valueBn": 1.313,
        "sourceUrl": "https://www.sec.gov/Archives/edgar/data/1018724/000101872424000161/amzn-20240930_htm.xml",
        "sourceForm": "10-Q",
        "filingDate": "2024-11-01",
        "periodStart": "2024-07-01",
        "periodEnd": "2024-09-30"
      }
    ],
    "2024Q4": [
      {
        "name": "Online Stores",
        "memberKey": "onlinestores",
        "valueBn": 75.556,
        "sourceUrl": "https://www.sec.gov/Archives/edgar/data/1018724/000101872425000004/amzn-20241231_htm.xml",
        "sourceForm": "10-K",
        "filingDate": "2025-02-07",
        "periodStart": "2024-10-01",
        "periodEnd": "2024-12-31"
      },
      {
        "name": "Third Party Seller Services",
        "memberKey": "thirdpartysellerservices",
        "valueBn": 47.485,
        "sourceUrl": "https://www.sec.gov/Archives/edgar/data/1018724/000101872425000004/amzn-20241231_htm.xml",
        "sourceForm": "10-K",
        "filingDate": "2025-02-07",
        "periodStart": "2024-10-01",
        "periodEnd": "2024-12-31"
      },
      {
        "name": "Amazon Web Services",
        "memberKey": "amazonwebservices",
        "valueBn": 28.786,
        "sourceUrl": "https://www.sec.gov/Archives/edgar/data/1018724/000101872425000004/amzn-20241231_htm.xml",
        "sourceForm": "10-K",
        "filingDate": "2025-02-07",
        "periodStart": "2024-10-01",
        "periodEnd": "2024-12-31"
      },
      {
        "name": "Subscription Services",
        "memberKey": "subscriptionservices",
        "valueBn": 11.508,
        "sourceUrl": "https://www.sec.gov/Archives/edgar/data/1018724/000101872425000004/amzn-20241231_htm.xml",
        "sourceForm": "10-K",
        "filingDate": "2025-02-07",
        "periodStart": "2024-10-01",
        "periodEnd": "2024-12-31"
      },
      {
        "name": "Physical Stores",
        "memberKey": "physicalstores",
        "valueBn": 5.579,
        "sourceUrl": "https://www.sec.gov/Archives/edgar/data/1018724/000101872425000004/amzn-20241231_htm.xml",
        "sourceForm": "10-K",
        "filingDate": "2025-02-07",
        "periodStart": "2024-10-01",
        "periodEnd": "2024-12-31"
      },
      {
        "name": "Other Services",
        "memberKey": "otherservices",
        "valueBn": 1.59,
        "sourceUrl": "https://www.sec.gov/Archives/edgar/data/1018724/000101872425000004/amzn-20241231_htm.xml",
        "sourceForm": "10-K",
        "filingDate": "2025-02-07",
        "periodStart": "2024-10-01",
        "periodEnd": "2024-12-31"
      }
    ],
    "2025Q1": [
      {
        "name": "Online Stores",
        "memberKey": "onlinestores",
        "valueBn": 57.407,
        "sourceUrl": "https://www.sec.gov/Archives/edgar/data/1018724/000101872425000036/amzn-20250331_htm.xml",
        "sourceForm": "10-Q",
        "filingDate": "2025-05-02",
        "periodStart": "2025-01-01",
        "periodEnd": "2025-03-31"
      },
      {
        "name": "Third Party Seller Services",
        "memberKey": "thirdpartysellerservices",
        "valueBn": 36.512,
        "sourceUrl": "https://www.sec.gov/Archives/edgar/data/1018724/000101872425000036/amzn-20250331_htm.xml",
        "sourceForm": "10-Q",
        "filingDate": "2025-05-02",
        "periodStart": "2025-01-01",
        "periodEnd": "2025-03-31"
      },
      {
        "name": "Amazon Web Services",
        "memberKey": "amazonwebservices",
        "valueBn": 29.267,
        "sourceUrl": "https://www.sec.gov/Archives/edgar/data/1018724/000101872425000036/amzn-20250331_htm.xml",
        "sourceForm": "10-Q",
        "filingDate": "2025-05-02",
        "periodStart": "2025-01-01",
        "periodEnd": "2025-03-31"
      },
      {
        "name": "Advertising Services",
        "memberKey": "advertisingservices",
        "valueBn": 13.921,
        "sourceUrl": "https://www.sec.gov/Archives/edgar/data/1018724/000101872425000036/amzn-20250331_htm.xml",
        "sourceForm": "10-Q",
        "filingDate": "2025-05-02",
        "periodStart": "2025-01-01",
        "periodEnd": "2025-03-31"
      },
      {
        "name": "Subscription Services",
        "memberKey": "subscriptionservices",
        "valueBn": 11.715,
        "sourceUrl": "https://www.sec.gov/Archives/edgar/data/1018724/000101872425000036/amzn-20250331_htm.xml",
        "sourceForm": "10-Q",
        "filingDate": "2025-05-02",
        "periodStart": "2025-01-01",
        "periodEnd": "2025-03-31"
      },
      {
        "name": "Physical Stores",
        "memberKey": "physicalstores",
        "valueBn": 5.533,
        "sourceUrl": "https://www.sec.gov/Archives/edgar/data/1018724/000101872425000036/amzn-20250331_htm.xml",
        "sourceForm": "10-Q",
        "filingDate": "2025-05-02",
        "periodStart": "2025-01-01",
        "periodEnd": "2025-03-31"
      },
      {
        "name": "Other Services",
        "memberKey": "otherservices",
        "valueBn": 1.312,
        "sourceUrl": "https://www.sec.gov/Archives/edgar/data/1018724/000101872425000036/amzn-20250331_htm.xml",
        "sourceForm": "10-Q",
        "filingDate": "2025-05-02",
        "periodStart": "2025-01-01",
        "periodEnd": "2025-03-31"
      }
    ],
    "2025Q2": [
      {
        "name": "Online Stores",
        "memberKey": "onlinestores",
        "valueBn": 61.485,
        "sourceUrl": "https://www.sec.gov/Archives/edgar/data/1018724/000101872425000086/amzn-20250630_htm.xml",
        "sourceForm": "10-Q",
        "filingDate": "2025-08-01",
        "periodStart": "2025-04-01",
        "periodEnd": "2025-06-30"
      },
      {
        "name": "Third Party Seller Services",
        "memberKey": "thirdpartysellerservices",
        "valueBn": 40.348,
        "sourceUrl": "https://www.sec.gov/Archives/edgar/data/1018724/000101872425000086/amzn-20250630_htm.xml",
        "sourceForm": "10-Q",
        "filingDate": "2025-08-01",
        "periodStart": "2025-04-01",
        "periodEnd": "2025-06-30"
      },
      {
        "name": "Amazon Web Services",
        "memberKey": "amazonwebservices",
        "valueBn": 30.873,
        "sourceUrl": "https://www.sec.gov/Archives/edgar/data/1018724/000101872425000086/amzn-20250630_htm.xml",
        "sourceForm": "10-Q",
        "filingDate": "2025-08-01",
        "periodStart": "2025-04-01",
        "periodEnd": "2025-06-30"
      },
      {
        "name": "Advertising Services",
        "memberKey": "advertisingservices",
        "valueBn": 15.694,
        "sourceUrl": "https://www.sec.gov/Archives/edgar/data/1018724/000101872425000086/amzn-20250630_htm.xml",
        "sourceForm": "10-Q",
        "filingDate": "2025-08-01",
        "periodStart": "2025-04-01",
        "periodEnd": "2025-06-30"
      },
      {
        "name": "Subscription Services",
        "memberKey": "subscriptionservices",
        "valueBn": 12.208,
        "sourceUrl": "https://www.sec.gov/Archives/edgar/data/1018724/000101872425000086/amzn-20250630_htm.xml",
        "sourceForm": "10-Q",
        "filingDate": "2025-08-01",
        "periodStart": "2025-04-01",
        "periodEnd": "2025-06-30"
      },
      {
        "name": "Physical Stores",
        "memberKey": "physicalstores",
        "valueBn": 5.595,
        "sourceUrl": "https://www.sec.gov/Archives/edgar/data/1018724/000101872425000086/amzn-20250630_htm.xml",
        "sourceForm": "10-Q",
        "filingDate": "2025-08-01",
        "periodStart": "2025-04-01",
        "periodEnd": "2025-06-30"
      },
      {
        "name": "Other Services",
        "memberKey": "otherservices",
        "valueBn": 1.499,
        "sourceUrl": "https://www.sec.gov/Archives/edgar/data/1018724/000101872425000086/amzn-20250630_htm.xml",
        "sourceForm": "10-Q",
        "filingDate": "2025-08-01",
        "periodStart": "2025-04-01",
        "periodEnd": "2025-06-30"
      }
    ],
    "2025Q3": [
      {
        "name": "Online Stores",
        "memberKey": "onlinestores",
        "valueBn": 67.407,
        "sourceUrl": "https://www.sec.gov/Archives/edgar/data/1018724/000101872425000123/amzn-20250930_htm.xml",
        "sourceForm": "10-Q",
        "filingDate": "2025-10-31",
        "periodStart": "2025-07-01",
        "periodEnd": "2025-09-30"
      },
      {
        "name": "Third Party Seller Services",
        "memberKey": "thirdpartysellerservices",
        "valueBn": 42.486,
        "sourceUrl": "https://www.sec.gov/Archives/edgar/data/1018724/000101872425000123/amzn-20250930_htm.xml",
        "sourceForm": "10-Q",
        "filingDate": "2025-10-31",
        "periodStart": "2025-07-01",
        "periodEnd": "2025-09-30"
      },
      {
        "name": "Amazon Web Services",
        "memberKey": "amazonwebservices",
        "valueBn": 33.006,
        "sourceUrl": "https://www.sec.gov/Archives/edgar/data/1018724/000101872425000123/amzn-20250930_htm.xml",
        "sourceForm": "10-Q",
        "filingDate": "2025-10-31",
        "periodStart": "2025-07-01",
        "periodEnd": "2025-09-30"
      },
      {
        "name": "Advertising Services",
        "memberKey": "advertisingservices",
        "valueBn": 17.703,
        "sourceUrl": "https://www.sec.gov/Archives/edgar/data/1018724/000101872425000123/amzn-20250930_htm.xml",
        "sourceForm": "10-Q",
        "filingDate": "2025-10-31",
        "periodStart": "2025-07-01",
        "periodEnd": "2025-09-30"
      },
      {
        "name": "Subscription Services",
        "memberKey": "subscriptionservices",
        "valueBn": 12.574,
        "sourceUrl": "https://www.sec.gov/Archives/edgar/data/1018724/000101872425000123/amzn-20250930_htm.xml",
        "sourceForm": "10-Q",
        "filingDate": "2025-10-31",
        "periodStart": "2025-07-01",
        "periodEnd": "2025-09-30"
      },
      {
        "name": "Physical Stores",
        "memberKey": "physicalstores",
        "valueBn": 5.578,
        "sourceUrl": "https://www.sec.gov/Archives/edgar/data/1018724/000101872425000123/amzn-20250930_htm.xml",
        "sourceForm": "10-Q",
        "filingDate": "2025-10-31",
        "periodStart": "2025-07-01",
        "periodEnd": "2025-09-30"
      },
      {
        "name": "Other Services",
        "memberKey": "otherservices",
        "valueBn": 1.415,
        "sourceUrl": "https://www.sec.gov/Archives/edgar/data/1018724/000101872425000123/amzn-20250930_htm.xml",
        "sourceForm": "10-Q",
        "filingDate": "2025-10-31",
        "periodStart": "2025-07-01",
        "periodEnd": "2025-09-30"
      }
    ],
    "2025Q4": [
      {
        "name": "Online Stores",
        "memberKey": "onlinestores",
        "valueBn": 82.988,
        "sourceUrl": "https://www.sec.gov/Archives/edgar/data/1018724/000101872426000004/amzn-20251231_htm.xml",
        "sourceForm": "10-K",
        "filingDate": "2026-02-06",
        "periodStart": "2025-10-01",
        "periodEnd": "2025-12-31"
      },
      {
        "name": "Third Party Seller Services",
        "memberKey": "thirdpartysellerservices",
        "valueBn": 52.816,
        "sourceUrl": "https://www.sec.gov/Archives/edgar/data/1018724/000101872426000004/amzn-20251231_htm.xml",
        "sourceForm": "10-K",
        "filingDate": "2026-02-06",
        "periodStart": "2025-10-01",
        "periodEnd": "2025-12-31"
      },
      {
        "name": "Amazon Web Services",
        "memberKey": "amazonwebservices",
        "valueBn": 35.579,
        "sourceUrl": "https://www.sec.gov/Archives/edgar/data/1018724/000101872426000004/amzn-20251231_htm.xml",
        "sourceForm": "10-K",
        "filingDate": "2026-02-06",
        "periodStart": "2025-10-01",
        "periodEnd": "2025-12-31"
      },
      {
        "name": "Subscription Services",
        "memberKey": "subscriptionservices",
        "valueBn": 13.122,
        "sourceUrl": "https://www.sec.gov/Archives/edgar/data/1018724/000101872426000004/amzn-20251231_htm.xml",
        "sourceForm": "10-K",
        "filingDate": "2026-02-06",
        "periodStart": "2025-10-01",
        "periodEnd": "2025-12-31"
      },
      {
        "name": "Physical Stores",
        "memberKey": "physicalstores",
        "valueBn": 5.855,
        "sourceUrl": "https://www.sec.gov/Archives/edgar/data/1018724/000101872426000004/amzn-20251231_htm.xml",
        "sourceForm": "10-K",
        "filingDate": "2026-02-06",
        "periodStart": "2025-10-01",
        "periodEnd": "2025-12-31"
      },
      {
        "name": "Other Services",
        "memberKey": "otherservices",
        "valueBn": 1.709,
        "sourceUrl": "https://www.sec.gov/Archives/edgar/data/1018724/000101872426000004/amzn-20251231_htm.xml",
        "sourceForm": "10-K",
        "filingDate": "2026-02-06",
        "periodStart": "2025-10-01",
        "periodEnd": "2025-12-31"
      }
    ]
  },
  "filingsUsed": [
    {
      "form": "10-K",
      "filingDate": "2026-02-06",
      "accession": "0001018724-26-000004",
      "primaryDocument": "amzn-20251231.htm",
      "instance": "amzn-20251231_htm.xml"
    },
    {
      "form": "10-Q",
      "filingDate": "2025-10-31",
      "accession": "0001018724-25-000123",
      "primaryDocument": "amzn-20250930.htm",
      "instance": "amzn-20250930_htm.xml"
    },
    {
      "form": "10-Q",
      "filingDate": "2025-08-01",
      "accession": "0001018724-25-000086",
      "primaryDocument": "amzn-20250630.htm",
      "instance": "amzn-20250630_htm.xml"
    },
    {
      "form": "10-Q",
      "filingDate": "2025-05-02",
      "accession": "0001018724-25-000036",
      "primaryDocument": "amzn-20250331.htm",
      "instance": "amzn-20250331_htm.xml"
    },
    {
      "form": "10-K",
      "filingDate": "2025-02-07",
      "accession": "0001018724-25-000004",
      "primaryDocument": "amzn-20241231.htm",
      "instance": "amzn-20241231_htm.xml"
    },
    {
      "form": "10-Q",
      "filingDate": "2024-11-01",
      "accession": "0001018724-24-000161",
      "primaryDocument": "amzn-20240930.htm",
      "instance": "amzn-20240930_htm.xml"
    },
    {
      "form": "10-Q",
      "filingDate": "2024-08-02",
      "accession": "0001018724-24-000130",
      "primaryDocument": "amzn-20240630.htm",
      "instance": "amzn-20240630_htm.xml"
    },
    {
      "form": "10-Q",
      "filingDate": "2024-05-01",
      "accession": "0001018724-24-000083",
      "primaryDocument": "amzn-20240331.htm",
      "instance": "amzn-20240331_htm.xml"
    },
    {
      "form": "10-K",
      "filingDate": "2024-02-02",
      "accession": "0001018724-24-000008",
      "primaryDocument": "amzn-20231231.htm",
      "instance": "amzn-20231231_htm.xml"
    },
    {
      "form": "10-Q",
      "filingDate": "2023-10-27",
      "accession": "0001018724-23-000018",
      "primaryDocument": "amzn-20230930.htm",
      "instance": "amzn-20230930_htm.xml"
    },
    {
      "form": "10-Q",
      "filingDate": "2023-08-04",
      "accession": "0001018724-23-000012",
      "primaryDocument": "amzn-20230630.htm",
      "instance": "amzn-20230630_htm.xml"
    },
    {
      "form": "10-Q",
      "filingDate": "2023-04-28",
      "accession": "0001018724-23-000008",
      "primaryDocument": "amzn-20230331.htm",
      "instance": "amzn-20230331_htm.xml"
    },
    {
      "form": "10-K",
      "filingDate": "2023-02-03",
      "accession": "0001018724-23-000004",
      "primaryDocument": "amzn-20221231.htm",
      "instance": "amzn-20221231_htm.xml"
    },
    {
      "form": "10-Q",
      "filingDate": "2022-10-28",
      "accession": "0001018724-22-000023",
      "primaryDocument": "amzn-20220930.htm",
      "instance": "amzn-20220930_htm.xml"
    },
    {
      "form": "10-Q",
      "filingDate": "2022-07-29",
      "accession": "0001018724-22-000019",
      "primaryDocument": "amzn-20220630.htm",
      "instance": "amzn-20220630_htm.xml"
    },
    {
      "form": "10-Q",
      "filingDate": "2022-04-29",
      "accession": "0001018724-22-000013",
      "primaryDocument": "amzn-20220331.htm",
      "instance": "amzn-20220331_htm.xml"
    },
    {
      "form": "10-K",
      "filingDate": "2022-02-04",
      "accession": "0001018724-22-000005",
      "primaryDocument": "amzn-20211231.htm",
      "instance": "amzn-20211231_htm.xml"
    },
    {
      "form": "10-Q",
      "filingDate": "2021-10-29",
      "accession": "0001018724-21-000028",
      "primaryDocument": "amzn-20210930.htm",
      "instance": "amzn-20210930_htm.xml"
    },
    {
      "form": "10-Q",
      "filingDate": "2021-07-30",
      "accession": "0001018724-21-000020",
      "primaryDocument": "amzn-20210630.htm",
      "instance": "amzn-20210630_htm.xml"
    },
    {
      "form": "10-Q",
      "filingDate": "2021-04-30",
      "accession": "0001018724-21-000010",
      "primaryDocument": "amzn-20210331.htm",
      "instance": "amzn-20210331_htm.xml"
    },
    {
      "form": "10-K",
      "filingDate": "2021-02-03",
      "accession": "0001018724-21-000004",
      "primaryDocument": "amzn-20201231.htm",
      "instance": "amzn-20201231_htm.xml"
    },
    {
      "form": "10-Q",
      "filingDate": "2020-10-30",
      "accession": "0001018724-20-000030",
      "primaryDocument": "amzn-20200930.htm",
      "instance": "amzn-20200930_htm.xml"
    },
    {
      "form": "10-Q",
      "filingDate": "2020-07-31",
      "accession": "0001018724-20-000021",
      "primaryDocument": "amzn-20200630.htm",
      "instance": "amzn-20200630_htm.xml"
    },
    {
      "form": "10-Q",
      "filingDate": "2020-05-01",
      "accession": "0001018724-20-000010",
      "primaryDocument": "amzn-20200331x10q.htm",
      "instance": "amzn-20200331x10q_htm.xml"
    },
    {
      "form": "10-K",
      "filingDate": "2020-01-31",
      "accession": "0001018724-20-000004",
      "primaryDocument": "amzn-20191231x10k.htm",
      "instance": "amzn-20191231x10k_htm.xml"
    },
    {
      "form": "10-Q",
      "filingDate": "2019-10-25",
      "accession": "0001018724-19-000089",
      "primaryDocument": "amzn-2019930x10q.htm",
      "instance": "amzn-2019930x10q_htm.xml"
    },
    {
      "form": "10-Q",
      "filingDate": "2019-07-26",
      "accession": "0001018724-19-000071",
      "primaryDocument": "amzn-2019630x10q.htm",
      "instance": "amzn-2019630x10q_htm.xml"
    },
    {
      "form": "10-Q",
      "filingDate": "2019-04-26",
      "accession": "0001018724-19-000043",
      "primaryDocument": "amzn-2019331x10q.htm",
      "instance": "amzn-20190331.xml"
    }
  ],
  "errors": []
}