{
  "version": "document-parser-v1",
  "url": "https://static.www.tencent.com/storage/uploads/2019/11/09/f0e8634db8e04724c4a56b16e39b3750.pdf",
  "final_url": "https://static.www.tencent.com/storage/uploads/2019/11/09/f0e8634db8e04724c4a56b16e39b3750.pdf",
  "content_type": "application/pdf",
  "kind": "pdf",
  "extraction_method": "pdf-text",
  "language_profile": "en",
  "text": "Page 1 of 10 \nFor Immediate Release \n \n \nTENCENT ANNOUNCES 2011 FIRST QUARTER RESULTS \n \nHong Kong, May 11, 2011 – Tencent Holdings Limited (“Tencent” or the “Company”, SEHK 00700), \na leading provider of Internet and mobile & telecommunications value-added services in China, \ntoday announced the unaudited consolidated results for the first quarter of 2011 ended March 31, \n2011. \n \n \nHighlights of the first quarter of 2011: \n \n§ Total revenues were RMB6,338.4 million (USD966.8 million 1), an increase of 14.7% over the \nfourth quarter of 2010 (“QoQ”) or an increase of 50.0% over the first quarter of 2010 (“YoY”)  \n§ Revenues from Internet value-added services ( “IVAS”) were RMB5,251.3 million (USD800.9 \nmillion), an increase of 19.8% QoQ or an increase of 55.0% YoY \n§ Revenues from mobile & telecommunications value-added services (“MVAS”) were RMB777.8 \nmillion (USD118.6 million), an increase of 6.8% QoQ or an increase of 25.8% YoY  \n§ Revenues from online advertising were RMB280.9 million (USD42.8 million), a decrease of \n27.6% QoQ or an increase of 37.5% YoY  \n§ Gross profit was RMB4,144.7 million (USD632.2 million), an increase of 12.3% QoQ or an \nincrease of 43.0% YoY.  Gross margin decreased to 65.4% from 66.8% last quarter \n§ Operating profit was RMB3,386.5 million (USD516.5 million), an increase of 27.7% QoQ or an \nincrease of 57.6% YoY.  Operating margin increased to 53.4% from 48.0% last quarter \nNon-GAAP operating profit2 was RMB3,119.9 million (USD475.9 million), an increase of 11.0% \nQoQ or an increase of 38.1% YoY.  Non-GAAP operating margin decreased to 49.2% from \n50.9% last quarter \n§ Profit for the period was RMB2,884.2 million (USD439.9 million), an increase of 30.3% QoQ or \nan increase of 60.0% YoY.  Net margin increased to 45.5% from 40.1% last quarter \nNon-GAAP profit for the period 2 was RMB2,601.6 million (USD396.8 million), an increase of \n9.8% QoQ or an increase of 36.1% YoY.  Non-GAAP net margin decreased to 41.0% from \n42.9% last quarter \n§ Profit attributable to equity holders of the Company for the period was RMB2,870.4 million \n(USD437.8 million), an increase of 30.4% QoQ or an increase of 61.0% YoY \nNon-GAAP profit attributable to equity holders of the Company for the period2 was RMB2,584.7 \nmillion (USD394.2 million), an increase of 9.7% QoQ or an increase of 36.8% YoY \n§ Basic earnings per share for the quarter were RMB1.575, and diluted earnings per share were \nRMB1.540. \n§ Key platform statistics: \n- Active Instant Messaging (“IM”) user accounts increased 4.1% QoQ to 674.3 million \n- Peak simultaneous online IM user accounts increased 7.6% QoQ to 137.2 million  \n- Active Qzone user accounts increased 2.6% QoQ to 504.8 million; active Pengyou \nuser accounts increased 19.9% QoQ to 101.4 million \n                                                \n1 Figures stated in USD are based on USD1 to RMB6.5564 \n2 see “Non-GAAP Financial Measures” section for more details on the reasons for presenting these measures \n \n \nPage 2 of 10 \n- Peak simultaneous online QQ Game (for mini casual games only) user accounts \nincreased 13.2% QoQ to 7.7 million \n- Fee-based IVAS registered subscriptions increased 10.0% QoQ to 72.3 million  \n- Fee-based MVAS registered subscriptions increased 10.6% QoQ to 27.2 million  \n \n \nMr. Ma Huateng, Chairman and CEO of Tencent, said, “During the first quarter in 2011, we \nperformed well in both operational and financial metrics, mainly benefiting from a strong holiday \nseason.  On the strategic front, we have strengthened our franchise in social networking services \nthrough continued growth of Qzone and Pegnyou, as well as made marked progress in growing \nour microblog service in terms of both user base and user activeness.   \n \n“Looking forward, we remain committed to making significant investments in our existing core \nbusinesses and new strategic initiatives including microblog, e-commerce, search, online security, \nonline video and international expansion.  Although these investments will put pressure on our \nshort-term financial performance, we believe they are necessary for our long-term competitiveness.  \nAs the competitive landscape of the Internet industry evolves rapidly, we have also been \naccelerating our open platform strategy to collaborate with more industry partners and to introduce \nmore third-party applications onto our platforms.  Through these continuous efforts, we aim to \ndrive long-term business growth and help build a healthier ecosystem for the Internet industry as a \nwhole.” \n \n \nFinancial Review for the First Quarter of 2011 \n \nIVAS revenues increased 19.8% QoQ to RMB5,251.3 million and represented 82.8% of our total \nrevenues for the first quarter of 2011.  Online gaming revenues increased 28.2% QoQ to \nRMB3,572.7 million, primarily reflecting increased monetisation of our major online games during \nthe Chinese New Year holidays and winter break for students.  Cross Fire registered strong \nrevenue growth in the quarter and underpinned the growth in online gaming revenues.  Growth in \nDNF and Qi Xiong Zheng Ba, as well as contribution from World of West, a hardcore 3D fantasy \nMMOG launched in the first quarter of the year, also contributed to the increase in online gaming \nrevenues.  For our community value-added services, revenues increased 5.1% QoQ to \nRMB1,678.6 million.  Qzone benefited from growth in item-based revenues driven by an \nincreased number of third-party social applications offered on the platform.  Revenues from QQ \nMembership increased primarily as a result of enhanced privileges and valued-added functions as \nwell as positive seasonality.  As for QQ Show, revenues were broadly stable compared to the \nprevious quarter. \n \nMVAS revenues increased 6.8% QoQ to RMB777.8 million and represented 12.3% of our total \nrevenues.  This primarily reflected growth in revenues from our bundled SMS packages as a \nresult of promotional activities launched during the holiday period, as well as an increase in \nrevenues from mobile SNS and mobile games.  On the other hand, the regulation of requiring \nservice providers to conduct double confirmation plus reminder services for monthly subscription \nand item sales continued to impact our MVAS revenues. \n \nOnline advertising revenues decreased 27.6% QoQ to RMB280.9 million and represented 4.4% of \n \n \nPage 3 of 10 \nour total revenues.  This primarily reflected weaker seasonality due to reduced activities of \nadvertisers around the Chinese New Year holidays. \n \n \nOther Key Financial Information for the First Quarter of 2011 \n \nShare-based compensation was RMB144.1 million for the first quarter of 2011 as compared with \nRMB144.2 million for the previous quarter.    \n \nCapital expenditure was RMB720.8 million for the first quarter of 2011 as compared with \nRMB481.0 million for the previous quarter.   \n  \nThe Company repurchased 400,000 shares on the Stock Exchange for an aggregate consideration \nof approximately RMB63.7 million before expenses as compared with 2,624,000 shares \nrepurchased for an aggregate consideration of approximately RMB310.2 million for the previous \nquarter. \n \nDonation made to the Tencent Charity Fund was RMB100.0 million for the first quarter of 2011. No \ndonation was made for the previous quarter. \n \nAs at March 31, 2011, net cash position totaled RMB18,129.2 million which excluded unsecured \nshort-term borrowings of RMB4,923.9 million.   \n \nThe total number of shares of the Company in issue was 1.837 billion. \n \n \nBusiness Review and Outlook \n \nIn the first quarter of 2011, our IVAS business benefited from increased monetisation of our major \nonline games during the Chinese New Year holidays and winter break for students.  Our \ncommunity value-added services also registered growth.  For MVAS, the business expanded \nfurther on the back of growth in our bundled SMS packages, mobile SNS and mobile games.  Our \nonline advertising business experienced sequential decline in revenues, reflecting weaker \nseasonality in the first quarter driven by reduced activities of advertisers around the Chinese New \nYear holidays.  For the second quarter of 2011, we expect weaker seasonality for IVAS mainly due \nto school examinations and fewer school holidays.  This negative seasonality may be more \nsevere than previous years as a higher percentage of our revenues is based on item sale and such \nitem-based revenues are more prone to seasonal fluctuation than subscription-based revenues.  \nWith an uncertain regulatory environment and impact of new policies, visibility of our MVAS \nbusiness would remain low.  Our online advertising business is expected to benefit from stronger \nseasonality in the second quarter.  As we previously indicated, we have entered into a new \ninvestment phase, during which we will make significant investments in our existing platforms and \nnew strategic initiatives.  We will continue to increase our strategic investments in areas that \ninclude microblog, e-commerce, search, online security, online video and international expansion. \n \n \n \n \n \nPage 4 of 10 \nIM Platform \n \nOur IM platform benefited from positive seasonality and increasing penetration of mobile Internet in \nChina.  At the end of the first quarter of 2011, active user accounts reached 674.3 million, \nrepresenting a quarter-on-quarter growth of 4.1%.  PCU for the quarter grew by 7.6% to 137.2 \nmillion.  Looking ahead, we expect the growth of our IM platform to slow down with the growing \nscale of Internet users in China as well as the reducing number of users maintaining multiple \naccounts to play our social games QQ Farm and QQ Ranch, as these games become more \nmature.   \n \nQQ.com \n \nIn the first quarter of 2011, QQ.com continued to register healthy growth in traffic, consolidating its \nposition as the leading Internet portal in China.  During the quarter, we continued to improve the \ncontent quality and user experience of QQ.com.  In addition, we focused on developing deeper \nintegration with our microblog so as to unleash cross-platform synergies. \n \nIVAS \n \nOur community value-added services registered growth in the first quarter of 2011 on the back of \npositive seasonality and recovery in the growth of subscribers following the significant security \nattack that we encountered in the previous quarter.  For Qzone, active user accounts grew by \n2.6% on a quarter-on-quarter basis to 504.8 million at the end of the quarter.  However, the \nyear-on-year growth rate decreased, mainly reflecting the growing scale of its user base as well as \nthe maturity of QQ Farm and QQ Ranch which resulted in a reduced number of users maintaining \nmultiple accounts.  Qzone also registered growth in item-based revenues in the quarter as more \nthird-party applications were available on the platform.  Pengyou, the largest real-name SNS \nplatform for university students and white collar communities in China, experienced continued \ngrowth with active user accounts increasing sequentially by 19.9% to 101.4 million at the end of the \nquarter.  For our microblog, registered user accounts have exceeded 160 million.  We are \nfocusing on growing our user base and increasing user activeness through introducing more \ncelebrity microblogs and enriching premium content.  We have also launched significant \nmarketing programs to promote the brand awareness of our microblog.  As for QQ Membership, \nthe first quarter of 2011 saw solid growth in subscription base as we enriched functionalities, \nbroadened lifestyle privileges and focused on cross-platform promotions.  QQ Show was helped \nby special promotions during the Chinese New Year holidays and registered modest growth. \n \nIn the first quarter of 2011, our online gaming business benefited from increased monetisation of \nour major advanced casual games and MMOGs during the holiday periods.  Riding on the \nintroduction of new play modes, Cross Fire registered significant growth in PCU and revenues \nduring the quarter.  New content and in-game promotions for DNF were also launched to increase \nusage and stickiness.  For QQ Game, PCU reached a historical high level of 7.7 million, mainly \ndriven by launch of new play modes for major games, enhanced cross-platform integration and, to \na lesser extent, positive impact of holidays.  In addition, we continued to implement our strategy of \ndiversifying our game portfolio through identifying attractive yet differentiated genres.  Qi Xiong \nZheng Ba, a major title in the web game sector, continued to register growth in user base and \n \n \nPage 5 of 10 \nrevenues during the quarter.  Meanwhile, Roco Kingdom has become a leading online game in \nthe children segment with its PCU increasing to 400,000.  We are aiming to launch more titles \nalong this strategy of differentiation. \n \nMVAS \n \nOur bundled SMS packages, mobile SNS and mobile games experienced solid growth in the first \nquarter of 2011.  Our WAP portal continued to register significant traffic increase as we enhanced \ncontent and user experience.  Looking ahead, we will continue to extend our PC-based services, \nincluding SNS and microblog, to different wireless platforms and customise our applications for a \nlarger variety of terminal devices.  On regulatory front, a new service cancellation policy, which is \nan extension to the “double confirmation plus reminder ” rule, has been introduced.  We expect \nthat the resultant negative impact would affect the business in the next few quarters. \n \nOnline advertising \n \nDue to weaker seasonality in the first quarter, our online advertising business experienced \nsequential decline in revenues.  Compared to the same period of last year, the business \nregistered solid growth, riding on our expanded client base, enhanced media influence and \nimproved awareness of the strengths of our platforms.  During the quarter, we launched a major \ncorporate brand advertising campaign to enhance our corporate image, which is expected to \nbenefit our advertising business over the longer term.  We are also stepping up our investments in \nbandwidth and content acquisition to position ourselves for the opportunities in video advertising.  \nUser base of QQ Live has registered healthy growth with PCU for the first quarter of 2011 reaching \n4.5 million, representing a quarter-on-quarter growth of 21.6%.  In March 2011, a web-based \nversion of QQ Live was launched to offer a more convenient channel for users to access our video \ncontent.  With our significant traffic on multiple platforms, we believe our investments in building \nour content, branding, technology and advertising team will bear fruit for our advertising business \nover the long run. \n \n# # # \n \n \n \nPage 6 of 10 \nAbout Tencent \n \nTencent aims to enrich the interactive online experience of Internet users by providing a \ncomprehensive range of Internet and wireless value-added services.  Through its various online \nplatforms, including Instant Messaging QQ, web portal QQ.com, the QQ Game platform under \nTencent Games, multi-media social networking service Qzone and wireless portal, Tencent \nservices the largest online community in China and fulfills the user ’s needs for communication, \ninformation, entertainment and e-Commerce on the Internet.    \n \nTencent has three main streams of revenues: Internet value-added services, mobile and \ntelecommunications value-added services and online advertising.    \n \nShares of Tencent Holdings Limited are traded on the Main Board of the Stock Exchange of Hong \nKong Limited, under stock code 00700.  The Company became one of the 43 constituents of the \nHang Seng Index (HSI) on June 10, 2008.  For more information, please visit www.tencent.com/ir. \n \n \nFor enquiries, please contact:  \nCatherine Chan Tel: (86) 755 86013388 ext 88369 or (852) 21795122 Email: cchan#tencent.com \nJane Yip Tel: (86) 755 86013388 ext 81374 or (852) 21795122 Email: janeyip#tencent.com   \n \n \nNon-GAAP Financial Measures \n \nTo supplement the consolidated results of the Company prepared in accordance with IFRS, certain \nnon-GAAP financial measures, including non-GAAP operating profit, non-GAAP operating margin, \nnon-GAAP profit for the period, non-GAAP net margin and non-GAAP profit attributable to equity \nholders of the Company, have been presented in this press release.  These non-GAAP financial \nmeasures should be considered in addition to, not as a substitute for, measures of the Company's \nfinancial performance prepared in accordance with IFRS.  In addition, these non-GAAP financial \nmeasures may be defined differently from similar terms used by other companies.   \n \nThe Company's management believes that the non-GAAP financial measures provide investors \nwith useful supplementary information to assess the performance of the Company ’s core \noperations by excluding certain non-cash items and certain impact of acquisitions. \n \nForward-Looking Statements \n \nThis press release contains forward-looking statements relating to the business outlook, forecast \nbusiness plans and growth strategies of the Company.  These forward-looking statements are \nbased on information currently available to the Company and are stated herein on the basis of the \noutlook at the time of this press release.  They are based on certain expectations, assumptions \nand premises, some of which are subjective or beyond our control.  These forward-looking \nstatements may prove to be incorrect and may not be realized in future.  Underlying the \nforward-looking statements is a large number of risks and uncertainties.  Further information \nregarding these risks and uncertainties is included in our other public disclosure documents on our \ncorporate website. \n \n \nPage 7 of 10 \nCONSOLIDATED INCOME STATEMENT \nIn RMB ‘000 (unless otherwise stated) \n \n Unaudited  Unaudited \n 1Q2011 4Q2010  1Q2011 1Q2010 \nRevenues 6,338,420 5,524,163  6,338,420 4,226,060 \n    Internet VAS  5,251,282 4,383,940  5,251,282 3,387,377 \n    Mobile & Telecom VAS 777,792 728,516  777,792 618,238 \n    Online Advertising  280,894 388,126  280,894 204,334 \n    Others 28,452 23,581  28,452 16,111 \nCost of revenues (2,193,729) (1,832,362)  (2,193,729) (1,328,355) \nGross profit 4,144,691 3,691,801  4,144,691 2,897,705 \nGross margin 65.4% 66.8%  65.4% 68.6% \nInterest income 100,662 79,467  100,662 57,191 \nOther gains/ (losses), net 339,069 23,437  339,069 (35,275) \nS&M expenses (300,453) (301,796)  (300,453) (185,417) \nG&A expenses (897,466) (840,407)  (897,466) (585,766) \nOperating profit 3,386,503 2,652,502  3,386,503 2,148,438 \nOperating margin 53.4% 48.0%  53.4% 50.8% \nFinance (costs)/income, net (3,869) 265  (3,869) (1,558) \nShare of profit of associates  37,854 37,127  37,854 12,913 \nShare of (loss)/profit of jointly controlled \nentities \n(4,297) 3,399  (4,297) - \nProfit before income tax 3,416,191 2,693,293  3,416,191 2,159,793 \nIncome tax expense (531,983) (480,011)  (531,983) (357,375) \nProfit for the period 2,884,208 2,213,282  2,884,208 1,802,418 \nNet margin 45.5% 40.1%  45.5% 42.7% \nAttributable to:      \n    Equity holders of the Company 2,870,374 2,200,818  2,870,374 1,783,194 \n    Non-controlling interests 13,834 12,464  13,834 19,224 \n      \nNon-GAAP profit attributable to equity \nholders of the Company \n2,584,720 2,356,624  2,584,720 1,889,885 \n      \nEarnings per share (GAAP)      \n- basic (RMB) 1.575 1.209  1.575 0.984 \n- diluted (RMB) 1.540 1.182  1.540 0.959 \n \n \n \n \n \nPage 8 of 10 \n \nCONSOLIDATED STATEMENT OF COMPREHENSIVE INCOME \nIn RMB ‘000 (unless otherwise stated) \n \n Unaudited  Unaudited \n 1Q2011 4Q2010  1Q2011 1Q2010 \nProfit for the period 2,884,208 2,213,282  2,884,208 1,802,418 \nOther comprehensive income:      \n(Losses)/income from changes in fair \nvalue of available-for-sale financial \nassets \n(682,436) 1,821,129  (682,436) - \nCurrency translation differences 207 -  207 - \nTotal comprehensive income for the \nperiod \n2,201,979 4,034,411  2,201,979 1,802,418 \nAttributable to:      \n    Equity holders of the Company 2,188,145 4,021,947  2,188,145 1,783,194 \n    Non-controlling interests 13,834 12,464  13,834 19,224 \n \n \n \nPage 9 of 10 \nCONSOLIDATED STATEMENT OF FINANCIAL POSITION \n  In RMB ‘000 (unless otherwise stated) Unaudited    Audited  \n   31 March             31 December \n    2011 \n2010 \n  2010 \n2009 ASSETS    \nNon-current assets     \nFixed assets   4,095,980 3,292,828 \nConstruction in progress 17,682 386,943 \nInvestment properties 37,043 37,229 \nland use rights 228,711 229,890 \nIntangible assets 3,097,395  572,981 \nInvestment in associates 1,713,489  1,070,633 \nInvestment in jointly controlled entities 71,245  74,542 \nDeferred income tax assets 204,495  219,019 \nAvailable-for-sale financial assets 3,635,123  4,126,878 \nPrepayments, deposits and other assets 490,926  445,430 \n 13,592,089  10,456,373 \nCurrent assets    \nAccounts receivable 2,070,013 1,715,412 \nPrepayments, deposits and other assets 682,210 487,872 \nTerm deposits with initial term of over three months 12,170,143 11,725,743 \nRestricted cash 2,330,410 1,036,457 \nCash and cash equivalents  10,882,954 10,408,257 \n 28,135,730 25,373,741 \nTotal assets 41,727,819 35,830,114 \n    \nEQUITY    \nEquity attributable to the Company’s equity holders     \nShare capital 198 198 \nShare premium 1,049,294 1,100,302 \nShares held for share award scheme (346,988) (258,137) \nShare-based compensation reserve 1,343,923 1,199,663 \nOther reserves 566,481 1,919,695 \nRetained earnings 20,665,599 17,795,225 \n 23,278,507 21,756,946 \nNon-controlling interests 284,838 83,912 \nTotal equity 23,563,345 21,840,858 \n    \nLIABILITIES    \nNon-current liabilities    \nDeferred income tax liabilities 858,315 967,211 \nLong-term payables 980,214 - \n 1,838,529 967,211 \nCurrent liabilities   \nAccounts payable 2,046,669 1,380,464 \nOther payables and accruals 2,844,696 2,997,808 \nDerivative financial instruments 39,338 17,964 \nShort-term bank borrowings 7,131,801 5,298,947 \nCurrent income tax liabilities 452,768 341,103 \nOther tax liabilities 346,115 225,188 \nDeferred revenue 3,464,558 2,760,571 \n 16,325,945 13,022,045  \nTotal liabilities 18,164,474 13,989,256  \n    Total equity and liabilities 41,727,819 35,830,114 \n \nPage 10 of 10 \nRECONCILIATIONS OF IFRS TO NON-GAAP RESULTS \n \n  \nAs  \nreported \nAdjustments  \nIn RMB ‘000 \nexcept percentages \nShare-based \ncompensation \nGain on deemed \ndisposal of \npreviously held \ninterest in an \nassociate \nAmortisation of \nintangible assets \nresulting from \nacquisitions, net of \nrelated deferred tax \nPut options granted to employees of \ninvestees on their shares and shares \nto be issued under investees' \nshare-based incentive plans which \ncan be acquired by the Group \nNon-GAAP \nUnaudited three months ended 31 March 2011* \nOperating profit 3,386,503 144,123 (459,037) 39,230 9,091 3,119,910 \nOperating margin 53.4%     49.2% \nProfit for the period  2,884,208 144,123 (459,037) 23,229 9,091 2,601,614 \nNet margin 45.5%     41.0% \nProfit attributable to equity \nholders of the Company 2,870,374 143,121 (459,037) 21,827 8,435 2,584,720 \nUnaudited three months ended 31 December 2010 \nOperating profit 2,652,502 144,159 - 13,167 - 2,809,828 \nOperating margin 48.0%     50.9% \nProfit for the period  2,213,282 144,159 - 11,726 - 2,369,167 \nNet margin 40.1%     42.9% \nProfit attributable to equity \nholders of the Company 2,200,818 144,159 - 11,647 - 2,356,624 \nUnaudited three months ended 31 March 2010 \nOperating profit 2,148,438 100,972 - 9,513 - 2,258,923 \nOperating margin 50.8%     53.5% \nProfit for the period  1,802,418 100,972 - 7,759 - 1,911,149 \nNet margin 42.7%     45.2% \nProfit attributable to equity \nholders of the Company 1,783,194 100,972 - 5,719 - 1,889,885 \n* Note: The figures above include the impact of the Riot Games Acquisition which was closed on 18 February 2011.",
  "page_texts": [
    " \n \nPage 1 of 10 \nFor Immediate Release \n \n \nTENCENT ANNOUNCES 2011 FIRST QUARTER RESULTS \n \nHong Kong, May 11, 2011 – Tencent Holdings Limited (“Tencent” or the “Company”, SEHK 00700), \na leading provider of Internet and mobile & telecommunications value-added services in China, \ntoday announced the unaudited consolidated results for the first quarter of 2011 ended March 31, \n2011. \n \n \nHighlights of the first quarter of 2011: \n \n§ Total revenues were RMB6,338.4 million (USD966.8 million 1), an increase of 14.7% over the \nfourth quarter of 2010 (“QoQ”) or an increase of 50.0% over the first quarter of 2010 (“YoY”)  \n§ Revenues from Internet value-added services ( “IVAS”) were RMB5,251.3 million (USD800.9 \nmillion), an increase of 19.8% QoQ or an increase of 55.0% YoY \n§ Revenues from mobile & telecommunications value-added services (“MVAS”) were RMB777.8 \nmillion (USD118.6 million), an increase of 6.8% QoQ or an increase of 25.8% YoY  \n§ Revenues from online advertising were RMB280.9 million (USD42.8 million), a decrease of \n27.6% QoQ or an increase of 37.5% YoY  \n§ Gross profit was RMB4,144.7 million (USD632.2 million), an increase of 12.3% QoQ or an \nincrease of 43.0% YoY.  Gross margin decreased to 65.4% from 66.8% last quarter \n§ Operating profit was RMB3,386.5 million (USD516.5 million), an increase of 27.7% QoQ or an \nincrease of 57.6% YoY.  Operating margin increased to 53.4% from 48.0% last quarter \nNon-GAAP operating profit2 was RMB3,119.9 million (USD475.9 million), an increase of 11.0% \nQoQ or an increase of 38.1% YoY.  Non-GAAP operating margin decreased to 49.2% from \n50.9% last quarter \n§ Profit for the period was RMB2,884.2 million (USD439.9 million), an increase of 30.3% QoQ or \nan increase of 60.0% YoY.  Net margin increased to 45.5% from 40.1% last quarter \nNon-GAAP profit for the period 2 was RMB2,601.6 million (USD396.8 million), an increase of \n9.8% QoQ or an increase of 36.1% YoY.  Non-GAAP net margin decreased to 41.0% from \n42.9% last quarter \n§ Profit attributable to equity holders of the Company for the period was RMB2,870.4 million \n(USD437.8 million), an increase of 30.4% QoQ or an increase of 61.0% YoY \nNon-GAAP profit attributable to equity holders of the Company for the period2 was RMB2,584.7 \nmillion (USD394.2 million), an increase of 9.7% QoQ or an increase of 36.8% YoY \n§ Basic earnings per share for the quarter were RMB1.575, and diluted earnings per share were \nRMB1.540. \n§ Key platform statistics: \n- Active Instant Messaging (“IM”) user accounts increased 4.1% QoQ to 674.3 million \n- Peak simultaneous online IM user accounts increased 7.6% QoQ to 137.2 million  \n- Active Qzone user accounts increased 2.6% QoQ to 504.8 million; active Pengyou \nuser accounts increased 19.9% QoQ to 101.4 million \n                                                \n1 Figures stated in USD are based on USD1 to RMB6.5564 \n2 see “Non-GAAP Financial Measures” section for more details on the reasons for presenting these measures ",
    " \n \nPage 2 of 10 \n- Peak simultaneous online QQ Game (for mini casual games only) user accounts \nincreased 13.2% QoQ to 7.7 million \n- Fee-based IVAS registered subscriptions increased 10.0% QoQ to 72.3 million  \n- Fee-based MVAS registered subscriptions increased 10.6% QoQ to 27.2 million  \n \n \nMr. Ma Huateng, Chairman and CEO of Tencent, said, “During the first quarter in 2011, we \nperformed well in both operational and financial metrics, mainly benefiting from a strong holiday \nseason.  On the strategic front, we have strengthened our franchise in social networking services \nthrough continued growth of Qzone and Pegnyou, as well as made marked progress in growing \nour microblog service in terms of both user base and user activeness.   \n \n“Looking forward, we remain committed to making significant investments in our existing core \nbusinesses and new strategic initiatives including microblog, e-commerce, search, online security, \nonline video and international expansion.  Although these investments will put pressure on our \nshort-term financial performance, we believe they are necessary for our long-term competitiveness.  \nAs the competitive landscape of the Internet industry evolves rapidly, we have also been \naccelerating our open platform strategy to collaborate with more industry partners and to introduce \nmore third-party applications onto our platforms.  Through these continuous efforts, we aim to \ndrive long-term business growth and help build a healthier ecosystem for the Internet industry as a \nwhole.” \n \n \nFinancial Review for the First Quarter of 2011 \n \nIVAS revenues increased 19.8% QoQ to RMB5,251.3 million and represented 82.8% of our total \nrevenues for the first quarter of 2011.  Online gaming revenues increased 28.2% QoQ to \nRMB3,572.7 million, primarily reflecting increased monetisation of our major online games during \nthe Chinese New Year holidays and winter break for students.  Cross Fire registered strong \nrevenue growth in the quarter and underpinned the growth in online gaming revenues.  Growth in \nDNF and Qi Xiong Zheng Ba, as well as contribution from World of West, a hardcore 3D fantasy \nMMOG launched in the first quarter of the year, also contributed to the increase in online gaming \nrevenues.  For our community value-added services, revenues increased 5.1% QoQ to \nRMB1,678.6 million.  Qzone benefited from growth in item-based revenues driven by an \nincreased number of third-party social applications offered on the platform.  Revenues from QQ \nMembership increased primarily as a result of enhanced privileges and valued-added functions as \nwell as positive seasonality.  As for QQ Show, revenues were broadly stable compared to the \nprevious quarter. \n \nMVAS revenues increased 6.8% QoQ to RMB777.8 million and represented 12.3% of our total \nrevenues.  This primarily reflected growth in revenues from our bundled SMS packages as a \nresult of promotional activities launched during the holiday period, as well as an increase in \nrevenues from mobile SNS and mobile games.  On the other hand, the regulation of requiring \nservice providers to conduct double confirmation plus reminder services for monthly subscription \nand item sales continued to impact our MVAS revenues. \n \nOnline advertising revenues decreased 27.6% QoQ to RMB280.9 million and represented 4.4% of ",
    " \n \nPage 3 of 10 \nour total revenues.  This primarily reflected weaker seasonality due to reduced activities of \nadvertisers around the Chinese New Year holidays. \n \n \nOther Key Financial Information for the First Quarter of 2011 \n \nShare-based compensation was RMB144.1 million for the first quarter of 2011 as compared with \nRMB144.2 million for the previous quarter.    \n \nCapital expenditure was RMB720.8 million for the first quarter of 2011 as compared with \nRMB481.0 million for the previous quarter.   \n  \nThe Company repurchased 400,000 shares on the Stock Exchange for an aggregate consideration \nof approximately RMB63.7 million before expenses as compared with 2,624,000 shares \nrepurchased for an aggregate consideration of approximately RMB310.2 million for the previous \nquarter. \n \nDonation made to the Tencent Charity Fund was RMB100.0 million for the first quarter of 2011. No \ndonation was made for the previous quarter. \n \nAs at March 31, 2011, net cash position totaled RMB18,129.2 million which excluded unsecured \nshort-term borrowings of RMB4,923.9 million.   \n \nThe total number of shares of the Company in issue was 1.837 billion. \n \n \nBusiness Review and Outlook \n \nIn the first quarter of 2011, our IVAS business benefited from increased monetisation of our major \nonline games during the Chinese New Year holidays and winter break for students.  Our \ncommunity value-added services also registered growth.  For MVAS, the business expanded \nfurther on the back of growth in our bundled SMS packages, mobile SNS and mobile games.  Our \nonline advertising business experienced sequential decline in revenues, reflecting weaker \nseasonality in the first quarter driven by reduced activities of advertisers around the Chinese New \nYear holidays.  For the second quarter of 2011, we expect weaker seasonality for IVAS mainly due \nto school examinations and fewer school holidays.  This negative seasonality may be more \nsevere than previous years as a higher percentage of our revenues is based on item sale and such \nitem-based revenues are more prone to seasonal fluctuation than subscription-based revenues.  \nWith an uncertain regulatory environment and impact of new policies, visibility of our MVAS \nbusiness would remain low.  Our online advertising business is expected to benefit from stronger \nseasonality in the second quarter.  As we previously indicated, we have entered into a new \ninvestment phase, during which we will make significant investments in our existing platforms and \nnew strategic initiatives.  We will continue to increase our strategic investments in areas that \ninclude microblog, e-commerce, search, online security, online video and international expansion. \n \n \n ",
    " \n \nPage 4 of 10 \nIM Platform \n \nOur IM platform benefited from positive seasonality and increasing penetration of mobile Internet in \nChina.  At the end of the first quarter of 2011, active user accounts reached 674.3 million, \nrepresenting a quarter-on-quarter growth of 4.1%.  PCU for the quarter grew by 7.6% to 137.2 \nmillion.  Looking ahead, we expect the growth of our IM platform to slow down with the growing \nscale of Internet users in China as well as the reducing number of users maintaining multiple \naccounts to play our social games QQ Farm and QQ Ranch, as these games become more \nmature.   \n \nQQ.com \n \nIn the first quarter of 2011, QQ.com continued to register healthy growth in traffic, consolidating its \nposition as the leading Internet portal in China.  During the quarter, we continued to improve the \ncontent quality and user experience of QQ.com.  In addition, we focused on developing deeper \nintegration with our microblog so as to unleash cross-platform synergies. \n \nIVAS \n \nOur community value-added services registered growth in the first quarter of 2011 on the back of \npositive seasonality and recovery in the growth of subscribers following the significant security \nattack that we encountered in the previous quarter.  For Qzone, active user accounts grew by \n2.6% on a quarter-on-quarter basis to 504.8 million at the end of the quarter.  However, the \nyear-on-year growth rate decreased, mainly reflecting the growing scale of its user base as well as \nthe maturity of QQ Farm and QQ Ranch which resulted in a reduced number of users maintaining \nmultiple accounts.  Qzone also registered growth in item-based revenues in the quarter as more \nthird-party applications were available on the platform.  Pengyou, the largest real-name SNS \nplatform for university students and white collar communities in China, experienced continued \ngrowth with active user accounts increasing sequentially by 19.9% to 101.4 million at the end of the \nquarter.  For our microblog, registered user accounts have exceeded 160 million.  We are \nfocusing on growing our user base and increasing user activeness through introducing more \ncelebrity microblogs and enriching premium content.  We have also launched significant \nmarketing programs to promote the brand awareness of our microblog.  As for QQ Membership, \nthe first quarter of 2011 saw solid growth in subscription base as we enriched functionalities, \nbroadened lifestyle privileges and focused on cross-platform promotions.  QQ Show was helped \nby special promotions during the Chinese New Year holidays and registered modest growth. \n \nIn the first quarter of 2011, our online gaming business benefited from increased monetisation of \nour major advanced casual games and MMOGs during the holiday periods.  Riding on the \nintroduction of new play modes, Cross Fire registered significant growth in PCU and revenues \nduring the quarter.  New content and in-game promotions for DNF were also launched to increase \nusage and stickiness.  For QQ Game, PCU reached a historical high level of 7.7 million, mainly \ndriven by launch of new play modes for major games, enhanced cross-platform integration and, to \na lesser extent, positive impact of holidays.  In addition, we continued to implement our strategy of \ndiversifying our game portfolio through identifying attractive yet differentiated genres.  Qi Xiong \nZheng Ba, a major title in the web game sector, continued to register growth in user base and ",
    " \n \nPage 5 of 10 \nrevenues during the quarter.  Meanwhile, Roco Kingdom has become a leading online game in \nthe children segment with its PCU increasing to 400,000.  We are aiming to launch more titles \nalong this strategy of differentiation. \n \nMVAS \n \nOur bundled SMS packages, mobile SNS and mobile games experienced solid growth in the first \nquarter of 2011.  Our WAP portal continued to register significant traffic increase as we enhanced \ncontent and user experience.  Looking ahead, we will continue to extend our PC-based services, \nincluding SNS and microblog, to different wireless platforms and customise our applications for a \nlarger variety of terminal devices.  On regulatory front, a new service cancellation policy, which is \nan extension to the “double confirmation plus reminder ” rule, has been introduced.  We expect \nthat the resultant negative impact would affect the business in the next few quarters. \n \nOnline advertising \n \nDue to weaker seasonality in the first quarter, our online advertising business experienced \nsequential decline in revenues.  Compared to the same period of last year, the business \nregistered solid growth, riding on our expanded client base, enhanced media influence and \nimproved awareness of the strengths of our platforms.  During the quarter, we launched a major \ncorporate brand advertising campaign to enhance our corporate image, which is expected to \nbenefit our advertising business over the longer term.  We are also stepping up our investments in \nbandwidth and content acquisition to position ourselves for the opportunities in video advertising.  \nUser base of QQ Live has registered healthy growth with PCU for the first quarter of 2011 reaching \n4.5 million, representing a quarter-on-quarter growth of 21.6%.  In March 2011, a web-based \nversion of QQ Live was launched to offer a more convenient channel for users to access our video \ncontent.  With our significant traffic on multiple platforms, we believe our investments in building \nour content, branding, technology and advertising team will bear fruit for our advertising business \nover the long run. \n \n# # # \n ",
    " \n \nPage 6 of 10 \nAbout Tencent \n \nTencent aims to enrich the interactive online experience of Internet users by providing a \ncomprehensive range of Internet and wireless value-added services.  Through its various online \nplatforms, including Instant Messaging QQ, web portal QQ.com, the QQ Game platform under \nTencent Games, multi-media social networking service Qzone and wireless portal, Tencent \nservices the largest online community in China and fulfills the user ’s needs for communication, \ninformation, entertainment and e-Commerce on the Internet.    \n \nTencent has three main streams of revenues: Internet value-added services, mobile and \ntelecommunications value-added services and online advertising.    \n \nShares of Tencent Holdings Limited are traded on the Main Board of the Stock Exchange of Hong \nKong Limited, under stock code 00700.  The Company became one of the 43 constituents of the \nHang Seng Index (HSI) on June 10, 2008.  For more information, please visit www.tencent.com/ir. \n \n \nFor enquiries, please contact:  \nCatherine Chan Tel: (86) 755 86013388 ext 88369 or (852) 21795122 Email: cchan#tencent.com \nJane Yip Tel: (86) 755 86013388 ext 81374 or (852) 21795122 Email: janeyip#tencent.com   \n \n \nNon-GAAP Financial Measures \n \nTo supplement the consolidated results of the Company prepared in accordance with IFRS, certain \nnon-GAAP financial measures, including non-GAAP operating profit, non-GAAP operating margin, \nnon-GAAP profit for the period, non-GAAP net margin and non-GAAP profit attributable to equity \nholders of the Company, have been presented in this press release.  These non-GAAP financial \nmeasures should be considered in addition to, not as a substitute for, measures of the Company's \nfinancial performance prepared in accordance with IFRS.  In addition, these non-GAAP financial \nmeasures may be defined differently from similar terms used by other companies.   \n \nThe Company's management believes that the non-GAAP financial measures provide investors \nwith useful supplementary information to assess the performance of the Company ’s core \noperations by excluding certain non-cash items and certain impact of acquisitions. \n \nForward-Looking Statements \n \nThis press release contains forward-looking statements relating to the business outlook, forecast \nbusiness plans and growth strategies of the Company.  These forward-looking statements are \nbased on information currently available to the Company and are stated herein on the basis of the \noutlook at the time of this press release.  They are based on certain expectations, assumptions \nand premises, some of which are subjective or beyond our control.  These forward-looking \nstatements may prove to be incorrect and may not be realized in future.  Underlying the \nforward-looking statements is a large number of risks and uncertainties.  Further information \nregarding these risks and uncertainties is included in our other public disclosure documents on our \ncorporate website. ",
    " \n \nPage 7 of 10 \nCONSOLIDATED INCOME STATEMENT \nIn RMB ‘000 (unless otherwise stated) \n \n Unaudited  Unaudited \n 1Q2011 4Q2010  1Q2011 1Q2010 \nRevenues 6,338,420 5,524,163  6,338,420 4,226,060 \n    Internet VAS  5,251,282 4,383,940  5,251,282 3,387,377 \n    Mobile & Telecom VAS 777,792 728,516  777,792 618,238 \n    Online Advertising  280,894 388,126  280,894 204,334 \n    Others 28,452 23,581  28,452 16,111 \nCost of revenues (2,193,729) (1,832,362)  (2,193,729) (1,328,355) \nGross profit 4,144,691 3,691,801  4,144,691 2,897,705 \nGross margin 65.4% 66.8%  65.4% 68.6% \nInterest income 100,662 79,467  100,662 57,191 \nOther gains/ (losses), net 339,069 23,437  339,069 (35,275) \nS&M expenses (300,453) (301,796)  (300,453) (185,417) \nG&A expenses (897,466) (840,407)  (897,466) (585,766) \nOperating profit 3,386,503 2,652,502  3,386,503 2,148,438 \nOperating margin 53.4% 48.0%  53.4% 50.8% \nFinance (costs)/income, net (3,869) 265  (3,869) (1,558) \nShare of profit of associates  37,854 37,127  37,854 12,913 \nShare of (loss)/profit of jointly controlled \nentities \n(4,297) 3,399  (4,297) - \nProfit before income tax 3,416,191 2,693,293  3,416,191 2,159,793 \nIncome tax expense (531,983) (480,011)  (531,983) (357,375) \nProfit for the period 2,884,208 2,213,282  2,884,208 1,802,418 \nNet margin 45.5% 40.1%  45.5% 42.7% \nAttributable to:      \n    Equity holders of the Company 2,870,374 2,200,818  2,870,374 1,783,194 \n    Non-controlling interests 13,834 12,464  13,834 19,224 \n      \nNon-GAAP profit attributable to equity \nholders of the Company \n2,584,720 2,356,624  2,584,720 1,889,885 \n      \nEarnings per share (GAAP)      \n- basic (RMB) 1.575 1.209  1.575 0.984 \n- diluted (RMB) 1.540 1.182  1.540 0.959 \n \n \n ",
    " \n \nPage 8 of 10 \n \nCONSOLIDATED STATEMENT OF COMPREHENSIVE INCOME \nIn RMB ‘000 (unless otherwise stated) \n \n Unaudited  Unaudited \n 1Q2011 4Q2010  1Q2011 1Q2010 \nProfit for the period 2,884,208 2,213,282  2,884,208 1,802,418 \nOther comprehensive income:      \n(Losses)/income from changes in fair \nvalue of available-for-sale financial \nassets \n(682,436) 1,821,129  (682,436) - \nCurrency translation differences 207 -  207 - \nTotal comprehensive income for the \nperiod \n2,201,979 4,034,411  2,201,979 1,802,418 \nAttributable to:      \n    Equity holders of the Company 2,188,145 4,021,947  2,188,145 1,783,194 \n    Non-controlling interests 13,834 12,464  13,834 19,224 \n ",
    " \n \nPage 9 of 10 \nCONSOLIDATED STATEMENT OF FINANCIAL POSITION \n  In RMB ‘000 (unless otherwise stated) Unaudited    Audited  \n   31 March             31 December \n    2011 \n2010 \n  2010 \n2009 ASSETS    \nNon-current assets     \nFixed assets   4,095,980 3,292,828 \nConstruction in progress 17,682 386,943 \nInvestment properties 37,043 37,229 \nland use rights 228,711 229,890 \nIntangible assets 3,097,395  572,981 \nInvestment in associates 1,713,489  1,070,633 \nInvestment in jointly controlled entities 71,245  74,542 \nDeferred income tax assets 204,495  219,019 \nAvailable-for-sale financial assets 3,635,123  4,126,878 \nPrepayments, deposits and other assets 490,926  445,430 \n 13,592,089  10,456,373 \nCurrent assets    \nAccounts receivable 2,070,013 1,715,412 \nPrepayments, deposits and other assets 682,210 487,872 \nTerm deposits with initial term of over three months 12,170,143 11,725,743 \nRestricted cash 2,330,410 1,036,457 \nCash and cash equivalents  10,882,954 10,408,257 \n 28,135,730 25,373,741 \nTotal assets 41,727,819 35,830,114 \n    \nEQUITY    \nEquity attributable to the Company’s equity holders     \nShare capital 198 198 \nShare premium 1,049,294 1,100,302 \nShares held for share award scheme (346,988) (258,137) \nShare-based compensation reserve 1,343,923 1,199,663 \nOther reserves 566,481 1,919,695 \nRetained earnings 20,665,599 17,795,225 \n 23,278,507 21,756,946 \nNon-controlling interests 284,838 83,912 \nTotal equity 23,563,345 21,840,858 \n    \nLIABILITIES    \nNon-current liabilities    \nDeferred income tax liabilities 858,315 967,211 \nLong-term payables 980,214 - \n 1,838,529 967,211 \nCurrent liabilities   \nAccounts payable 2,046,669 1,380,464 \nOther payables and accruals 2,844,696 2,997,808 \nDerivative financial instruments 39,338 17,964 \nShort-term bank borrowings 7,131,801 5,298,947 \nCurrent income tax liabilities 452,768 341,103 \nOther tax liabilities 346,115 225,188 \nDeferred revenue 3,464,558 2,760,571 \n 16,325,945 13,022,045  \nTotal liabilities 18,164,474 13,989,256  \n    Total equity and liabilities 41,727,819 35,830,114 ",
    " \nPage 10 of 10 \nRECONCILIATIONS OF IFRS TO NON-GAAP RESULTS \n \n  \nAs  \nreported \nAdjustments  \nIn RMB ‘000 \nexcept percentages \nShare-based \ncompensation \nGain on deemed \ndisposal of \npreviously held \ninterest in an \nassociate \nAmortisation of \nintangible assets \nresulting from \nacquisitions, net of \nrelated deferred tax \nPut options granted to employees of \ninvestees on their shares and shares \nto be issued under investees' \nshare-based incentive plans which \ncan be acquired by the Group \nNon-GAAP \nUnaudited three months ended 31 March 2011* \nOperating profit 3,386,503 144,123 (459,037) 39,230 9,091 3,119,910 \nOperating margin 53.4%     49.2% \nProfit for the period  2,884,208 144,123 (459,037) 23,229 9,091 2,601,614 \nNet margin 45.5%     41.0% \nProfit attributable to equity \nholders of the Company 2,870,374 143,121 (459,037) 21,827 8,435 2,584,720 \nUnaudited three months ended 31 December 2010 \nOperating profit 2,652,502 144,159 - 13,167 - 2,809,828 \nOperating margin 48.0%     50.9% \nProfit for the period  2,213,282 144,159 - 11,726 - 2,369,167 \nNet margin 40.1%     42.9% \nProfit attributable to equity \nholders of the Company 2,200,818 144,159 - 11,647 - 2,356,624 \nUnaudited three months ended 31 March 2010 \nOperating profit 2,148,438 100,972 - 9,513 - 2,258,923 \nOperating margin 50.8%     53.5% \nProfit for the period  1,802,418 100,972 - 7,759 - 1,911,149 \nNet margin 42.7%     45.2% \nProfit attributable to equity \nholders of the Company 1,783,194 100,972 - 5,719 - 1,889,885 \n* Note: The figures above include the impact of the Riot Games Acquisition which was closed on 18 February 2011. "
  ],
  "html_tables": [],
  "metadata": {
    "pageCount": 10
  }
}